<?xml version="1.0" encoding="UTF-8"?>
<!DOCTYPE TERM_EXTRACTION_RESULTS SYSTEM "yatea.dtd">

<TERM_EXTRACTION_RESULTS>
  <LIST_TERM_CANDIDATES>
    <TERM_CANDIDATE MNP_STATUS="0">
      <ID>term20</ID>
      <FORM>parc</FORM>
      <LEMMA>parc</LEMMA>
      <MORPHOSYNTACTIC_FEATURES>
	    <SYNTACTIC_CATEGORY>NOM</SYNTACTIC_CATEGORY>
      </MORPHOSYNTACTIC_FEATURES>
      <HEAD>term20</HEAD>
      <NUMBER_OCCURRENCES>1</NUMBER_OCCURRENCES>
      <LIST_OCCURRENCES>
      <OCCURRENCE>
        <ID>occ37</ID>
        <MNP>0</MNP>
        <DOC>0</DOC>
        <SENTENCE>1</SENTENCE>
        <START_POSITION>3</START_POSITION>
        <END_POSITION>7</END_POSITION>
        </OCCURRENCE>
      </LIST_OCCURRENCES>
      <TERM_CONFIDENCE>0.5</TERM_CONFIDENCE>
      <TERM_WEIGHTS>
            <WEIGHT name="CValue">0</WEIGHT>
            <WEIGHT name="CValue1">0</WEIGHT>
            <WEIGHT name="CValuePlus">0</WEIGHT>
            <WEIGHT name="CValuePlus1">2</WEIGHT>
            <WEIGHT name="CValueStar">N/A</WEIGHT>
            <WEIGHT name="CValueStarH">0</WEIGHT>
            <WEIGHT name="CValueStarM">N/A</WEIGHT>
            <WEIGHT name="CValueStarR">N/A</WEIGHT>
            <WEIGHT name="CValueWCard">0</WEIGHT>
            <WEIGHT name="CValueWCardPlus">2</WEIGHT>
            <WEIGHT name="D">1</WEIGHT>
            <WEIGHT name="DDW">0</WEIGHT>
            <WEIGHT name="Freq">1</WEIGHT>
            <WEIGHT name="IM">N/A</WEIGHT>
            <WEIGHT name="LLR">N/A</WEIGHT>
            <WEIGHT name="NormFreq">0.5</WEIGHT>
            <WEIGHT name="iLong">1</WEIGHT>
            <WEIGHT name="iTer">1</WEIGHT>
            <WEIGHT name="idf">0:0</WEIGHT>
            <WEIGHT name="ilnc">1</WEIGHT>
            <WEIGHT name="ilncFreq">1</WEIGHT>
            <WEIGHT name="nbdoc4tc">1</WEIGHT>
            <WEIGHT name="tf">0:1</WEIGHT>
            <WEIGHT name="tf-idf">0:0</WEIGHT>
      </TERM_WEIGHTS>
      <LOG_INFORMATION>YaTeA</LOG_INFORMATION>
    </TERM_CANDIDATE>
    <TERM_CANDIDATE MNP_STATUS="1">
      <ID>term34</ID>
      <FORM>Feu</FORM>
      <LEMMA>feu</LEMMA>
      <MORPHOSYNTACTIC_FEATURES>
	    <SYNTACTIC_CATEGORY>NOM</SYNTACTIC_CATEGORY>
      </MORPHOSYNTACTIC_FEATURES>
      <HEAD>term34</HEAD>
      <NUMBER_OCCURRENCES>1</NUMBER_OCCURRENCES>
      <LIST_OCCURRENCES>
      <OCCURRENCE>
        <ID>occ49</ID>
        <MNP>1</MNP>
        <DOC>0</DOC>
        <SENTENCE>0</SENTENCE>
        <START_POSITION>0</START_POSITION>
        <END_POSITION>3</END_POSITION>
        </OCCURRENCE>
      </LIST_OCCURRENCES>
      <TERM_CONFIDENCE>0.5</TERM_CONFIDENCE>
      <TERM_WEIGHTS>
            <WEIGHT name="CValue">0</WEIGHT>
            <WEIGHT name="CValue1">1</WEIGHT>
            <WEIGHT name="CValuePlus">0</WEIGHT>
            <WEIGHT name="CValuePlus1">1</WEIGHT>
            <WEIGHT name="CValueStar">N/A</WEIGHT>
            <WEIGHT name="CValueStarH">N/A</WEIGHT>
            <WEIGHT name="CValueStarM">N/A</WEIGHT>
            <WEIGHT name="CValueStarR">1</WEIGHT>
            <WEIGHT name="CValueWCard">0</WEIGHT>
            <WEIGHT name="CValueWCardPlus">0</WEIGHT>
            <WEIGHT name="D">1</WEIGHT>
            <WEIGHT name="DDW">0</WEIGHT>
            <WEIGHT name="Freq">1</WEIGHT>
            <WEIGHT name="IM">N/A</WEIGHT>
            <WEIGHT name="LLR">N/A</WEIGHT>
            <WEIGHT name="NormFreq">0.5</WEIGHT>
            <WEIGHT name="iLong">1</WEIGHT>
            <WEIGHT name="iTer">0.5</WEIGHT>
            <WEIGHT name="idf">0:0</WEIGHT>
            <WEIGHT name="ilnc">0</WEIGHT>
            <WEIGHT name="ilncFreq">0</WEIGHT>
            <WEIGHT name="nbdoc4tc">1</WEIGHT>
            <WEIGHT name="tf">0:1</WEIGHT>
            <WEIGHT name="tf-idf">0:0</WEIGHT>
      </TERM_WEIGHTS>
      <LOG_INFORMATION>YaTeA</LOG_INFORMATION>
    </TERM_CANDIDATE>
    <TERM_CANDIDATE MNP_STATUS="1">
      <ID>term19</ID>
      <FORM>parc éolien</FORM>
      <LEMMA>parc éolien</LEMMA>
      <MORPHOSYNTACTIC_FEATURES>
	    <SYNTACTIC_CATEGORY>NOM ADJ</SYNTACTIC_CATEGORY>
      </MORPHOSYNTACTIC_FEATURES>
      <HEAD>term20</HEAD>
      <NUMBER_OCCURRENCES>1</NUMBER_OCCURRENCES>
      <LIST_OCCURRENCES>
      <OCCURRENCE>
        <ID>occ4</ID>
        <MNP>1</MNP>
        <DOC>0</DOC>
        <SENTENCE>1</SENTENCE>
        <START_POSITION>3</START_POSITION>
        <END_POSITION>14</END_POSITION>
        </OCCURRENCE>
      </LIST_OCCURRENCES>
      <TERM_CONFIDENCE>0.5</TERM_CONFIDENCE>
      <TERM_WEIGHTS>
            <WEIGHT name="CValue">1</WEIGHT>
            <WEIGHT name="CValue1">1.58496250072116</WEIGHT>
            <WEIGHT name="CValuePlus">1</WEIGHT>
            <WEIGHT name="CValuePlus1">1.58496250072116</WEIGHT>
            <WEIGHT name="CValueStar">N/A</WEIGHT>
            <WEIGHT name="CValueStarH">N/A</WEIGHT>
            <WEIGHT name="CValueStarM">N/A</WEIGHT>
            <WEIGHT name="CValueStarR">0.584962500721156</WEIGHT>
            <WEIGHT name="CValueWCard">0</WEIGHT>
            <WEIGHT name="CValueWCardPlus">0</WEIGHT>
            <WEIGHT name="D">1</WEIGHT>
            <WEIGHT name="DDW">0</WEIGHT>
            <WEIGHT name="Freq">1</WEIGHT>
            <WEIGHT name="IM">2</WEIGHT>
            <WEIGHT name="LLR">0.000115129154648748</WEIGHT>
            <WEIGHT name="NormFreq">0.5</WEIGHT>
            <WEIGHT name="iLong">0.5</WEIGHT>
            <WEIGHT name="iTer">0.333333333333333</WEIGHT>
            <WEIGHT name="idf">0:0</WEIGHT>
            <WEIGHT name="ilnc">0</WEIGHT>
            <WEIGHT name="ilncFreq">0</WEIGHT>
            <WEIGHT name="nbdoc4tc">1</WEIGHT>
            <WEIGHT name="tf">0:1</WEIGHT>
            <WEIGHT name="tf-idf">0:0</WEIGHT>
      </TERM_WEIGHTS>
      <LOG_INFORMATION>YaTeA</LOG_INFORMATION>
      <SYNTACTIC_ANALYSIS>
        <HEAD>
        term20
        </HEAD>
        <MODIFIER POSITION="AFTER">
        term21
        </MODIFIER>
      </SYNTACTIC_ANALYSIS>
    </TERM_CANDIDATE>
    <TERM_CANDIDATE MNP_STATUS="1">
      <ID>term1</ID>
      <FORM>départ de feu.L&apos;éolienne sinistrée</FORM>
      <LEMMA>départ de feu.L&apos;éolienne sinistré</LEMMA>
      <MORPHOSYNTACTIC_FEATURES>
	    <SYNTACTIC_CATEGORY>NOM de NOM ADJ</SYNTACTIC_CATEGORY>
      </MORPHOSYNTACTIC_FEATURES>
      <HEAD>term2</HEAD>
      <NUMBER_OCCURRENCES>1</NUMBER_OCCURRENCES>
      <LIST_OCCURRENCES>
      <OCCURRENCE>
        <ID>occ15</ID>
        <MNP>1</MNP>
        <DOC>0</DOC>
        <SENTENCE>5</SENTENCE>
        <START_POSITION>58</START_POSITION>
        <END_POSITION>92</END_POSITION>
        </OCCURRENCE>
      </LIST_OCCURRENCES>
      <TERM_CONFIDENCE>0.5</TERM_CONFIDENCE>
      <TERM_WEIGHTS>
            <WEIGHT name="CValue">2</WEIGHT>
            <WEIGHT name="CValue1">2.32192809488736</WEIGHT>
            <WEIGHT name="CValuePlus">2</WEIGHT>
            <WEIGHT name="CValuePlus1">2.32192809488736</WEIGHT>
            <WEIGHT name="CValueStar">N/A</WEIGHT>
            <WEIGHT name="CValueStarH">N/A</WEIGHT>
            <WEIGHT name="CValueStarM">N/A</WEIGHT>
            <WEIGHT name="CValueStarR">0.321928094887362</WEIGHT>
            <WEIGHT name="CValueWCard">0</WEIGHT>
            <WEIGHT name="CValueWCardPlus">0</WEIGHT>
            <WEIGHT name="D">1</WEIGHT>
            <WEIGHT name="DDW">0</WEIGHT>
            <WEIGHT name="Freq">1</WEIGHT>
            <WEIGHT name="IM">2</WEIGHT>
            <WEIGHT name="LLR">0.000115129154648748</WEIGHT>
            <WEIGHT name="NormFreq">0.5</WEIGHT>
            <WEIGHT name="iLong">0.25</WEIGHT>
            <WEIGHT name="iTer">0.2</WEIGHT>
            <WEIGHT name="idf">0:0</WEIGHT>
            <WEIGHT name="ilnc">0</WEIGHT>
            <WEIGHT name="ilncFreq">0</WEIGHT>
            <WEIGHT name="nbdoc4tc">1</WEIGHT>
            <WEIGHT name="tf">0:1</WEIGHT>
            <WEIGHT name="tf-idf">0:0</WEIGHT>
      </TERM_WEIGHTS>
      <LOG_INFORMATION>YaTeA</LOG_INFORMATION>
      <SYNTACTIC_ANALYSIS>
        <HEAD>
        term2
        </HEAD>
        <MODIFIER POSITION="AFTER">
        term3
        </MODIFIER>
        <PREP>
        de
        </PREP>
      </SYNTACTIC_ANALYSIS>
    </TERM_CANDIDATE>
    <TERM_CANDIDATE MNP_STATUS="0">
      <ID>term2</ID>
      <FORM>départ</FORM>
      <LEMMA>départ</LEMMA>
      <MORPHOSYNTACTIC_FEATURES>
	    <SYNTACTIC_CATEGORY>NOM</SYNTACTIC_CATEGORY>
      </MORPHOSYNTACTIC_FEATURES>
      <HEAD>term2</HEAD>
      <NUMBER_OCCURRENCES>1</NUMBER_OCCURRENCES>
      <LIST_OCCURRENCES>
      <OCCURRENCE>
        <ID>occ23</ID>
        <MNP>0</MNP>
        <DOC>0</DOC>
        <SENTENCE>5</SENTENCE>
        <START_POSITION>58</START_POSITION>
        <END_POSITION>64</END_POSITION>
        </OCCURRENCE>
      </LIST_OCCURRENCES>
      <TERM_CONFIDENCE>0.5</TERM_CONFIDENCE>
      <TERM_WEIGHTS>
            <WEIGHT name="CValue">0</WEIGHT>
            <WEIGHT name="CValue1">0</WEIGHT>
            <WEIGHT name="CValuePlus">0</WEIGHT>
            <WEIGHT name="CValuePlus1">2</WEIGHT>
            <WEIGHT name="CValueStar">N/A</WEIGHT>
            <WEIGHT name="CValueStarH">0</WEIGHT>
            <WEIGHT name="CValueStarM">N/A</WEIGHT>
            <WEIGHT name="CValueStarR">N/A</WEIGHT>
            <WEIGHT name="CValueWCard">0</WEIGHT>
            <WEIGHT name="CValueWCardPlus">2</WEIGHT>
            <WEIGHT name="D">1</WEIGHT>
            <WEIGHT name="DDW">0</WEIGHT>
            <WEIGHT name="Freq">1</WEIGHT>
            <WEIGHT name="IM">N/A</WEIGHT>
            <WEIGHT name="LLR">N/A</WEIGHT>
            <WEIGHT name="NormFreq">0.5</WEIGHT>
            <WEIGHT name="iLong">1</WEIGHT>
            <WEIGHT name="iTer">1</WEIGHT>
            <WEIGHT name="idf">0:0</WEIGHT>
            <WEIGHT name="ilnc">1</WEIGHT>
            <WEIGHT name="ilncFreq">1</WEIGHT>
            <WEIGHT name="nbdoc4tc">1</WEIGHT>
            <WEIGHT name="tf">0:1</WEIGHT>
            <WEIGHT name="tf-idf">0:0</WEIGHT>
      </TERM_WEIGHTS>
      <LOG_INFORMATION>YaTeA</LOG_INFORMATION>
    </TERM_CANDIDATE>
    <TERM_CANDIDATE MNP_STATUS="0">
      <ID>term7</ID>
      <FORM>balisage</FORM>
      <LEMMA>balisage</LEMMA>
      <MORPHOSYNTACTIC_FEATURES>
	    <SYNTACTIC_CATEGORY>NOM</SYNTACTIC_CATEGORY>
      </MORPHOSYNTACTIC_FEATURES>
      <HEAD>term7</HEAD>
      <NUMBER_OCCURRENCES>1</NUMBER_OCCURRENCES>
      <LIST_OCCURRENCES>
      <OCCURRENCE>
        <ID>occ27</ID>
        <MNP>0</MNP>
        <DOC>0</DOC>
        <SENTENCE>4</SENTENCE>
        <START_POSITION>3</START_POSITION>
        <END_POSITION>11</END_POSITION>
        </OCCURRENCE>
      </LIST_OCCURRENCES>
      <TERM_CONFIDENCE>0.5</TERM_CONFIDENCE>
      <TERM_WEIGHTS>
            <WEIGHT name="CValue">0</WEIGHT>
            <WEIGHT name="CValue1">0</WEIGHT>
            <WEIGHT name="CValuePlus">0</WEIGHT>
            <WEIGHT name="CValuePlus1">2</WEIGHT>
            <WEIGHT name="CValueStar">N/A</WEIGHT>
            <WEIGHT name="CValueStarH">0</WEIGHT>
            <WEIGHT name="CValueStarM">N/A</WEIGHT>
            <WEIGHT name="CValueStarR">N/A</WEIGHT>
            <WEIGHT name="CValueWCard">0</WEIGHT>
            <WEIGHT name="CValueWCardPlus">2</WEIGHT>
            <WEIGHT name="D">1</WEIGHT>
            <WEIGHT name="DDW">0</WEIGHT>
            <WEIGHT name="Freq">1</WEIGHT>
            <WEIGHT name="IM">N/A</WEIGHT>
            <WEIGHT name="LLR">N/A</WEIGHT>
            <WEIGHT name="NormFreq">0.5</WEIGHT>
            <WEIGHT name="iLong">1</WEIGHT>
            <WEIGHT name="iTer">1</WEIGHT>
            <WEIGHT name="idf">0:0</WEIGHT>
            <WEIGHT name="ilnc">1</WEIGHT>
            <WEIGHT name="ilncFreq">1</WEIGHT>
            <WEIGHT name="nbdoc4tc">1</WEIGHT>
            <WEIGHT name="tf">0:1</WEIGHT>
            <WEIGHT name="tf-idf">0:0</WEIGHT>
      </TERM_WEIGHTS>
      <LOG_INFORMATION>YaTeA</LOG_INFORMATION>
    </TERM_CANDIDATE>
    <TERM_CANDIDATE MNP_STATUS="1">
      <ID>term23</ID>
      <FORM>éolienne de 2,5 MW</FORM>
      <LEMMA>éolienne de 2,5 MW</LEMMA>
      <MORPHOSYNTACTIC_FEATURES>
	    <SYNTACTIC_CATEGORY>NOM de NUM NOM</SYNTACTIC_CATEGORY>
      </MORPHOSYNTACTIC_FEATURES>
      <HEAD>term24</HEAD>
      <NUMBER_OCCURRENCES>1</NUMBER_OCCURRENCES>
      <LIST_OCCURRENCES>
      <OCCURRENCE>
        <ID>occ3</ID>
        <MNP>1</MNP>
        <DOC>0</DOC>
        <SENTENCE>0</SENTENCE>
        <START_POSITION>81</START_POSITION>
        <END_POSITION>99</END_POSITION>
        </OCCURRENCE>
      </LIST_OCCURRENCES>
      <TERM_CONFIDENCE>0.5</TERM_CONFIDENCE>
      <TERM_WEIGHTS>
            <WEIGHT name="CValue">2</WEIGHT>
            <WEIGHT name="CValue1">2.32192809488736</WEIGHT>
            <WEIGHT name="CValuePlus">2</WEIGHT>
            <WEIGHT name="CValuePlus1">2.32192809488736</WEIGHT>
            <WEIGHT name="CValueStar">N/A</WEIGHT>
            <WEIGHT name="CValueStarH">N/A</WEIGHT>
            <WEIGHT name="CValueStarM">N/A</WEIGHT>
            <WEIGHT name="CValueStarR">0.321928094887362</WEIGHT>
            <WEIGHT name="CValueWCard">0</WEIGHT>
            <WEIGHT name="CValueWCardPlus">0</WEIGHT>
            <WEIGHT name="D">1</WEIGHT>
            <WEIGHT name="DDW">0</WEIGHT>
            <WEIGHT name="Freq">1</WEIGHT>
            <WEIGHT name="IM">2</WEIGHT>
            <WEIGHT name="LLR">0.000115129154648748</WEIGHT>
            <WEIGHT name="NormFreq">0.5</WEIGHT>
            <WEIGHT name="iLong">0.25</WEIGHT>
            <WEIGHT name="iTer">0.2</WEIGHT>
            <WEIGHT name="idf">0:0</WEIGHT>
            <WEIGHT name="ilnc">0</WEIGHT>
            <WEIGHT name="ilncFreq">0</WEIGHT>
            <WEIGHT name="nbdoc4tc">1</WEIGHT>
            <WEIGHT name="tf">0:1</WEIGHT>
            <WEIGHT name="tf-idf">0:0</WEIGHT>
      </TERM_WEIGHTS>
      <LOG_INFORMATION>YaTeA</LOG_INFORMATION>
      <SYNTACTIC_ANALYSIS>
        <HEAD>
        term24
        </HEAD>
        <MODIFIER POSITION="AFTER">
        term25
        </MODIFIER>
        <PREP>
        de
        </PREP>
      </SYNTACTIC_ANALYSIS>
    </TERM_CANDIDATE>
    <TERM_CANDIDATE MNP_STATUS="1">
      <ID>term31</ID>
      <FORM>incident électrique</FORM>
      <LEMMA>incident électrique</LEMMA>
      <MORPHOSYNTACTIC_FEATURES>
	    <SYNTACTIC_CATEGORY>NOM ADJ</SYNTACTIC_CATEGORY>
      </MORPHOSYNTACTIC_FEATURES>
      <HEAD>term32</HEAD>
      <NUMBER_OCCURRENCES>1</NUMBER_OCCURRENCES>
      <LIST_OCCURRENCES>
      <OCCURRENCE>
        <ID>occ14</ID>
        <MNP>1</MNP>
        <DOC>0</DOC>
        <SENTENCE>5</SENTENCE>
        <START_POSITION>20</START_POSITION>
        <END_POSITION>39</END_POSITION>
        </OCCURRENCE>
      </LIST_OCCURRENCES>
      <TERM_CONFIDENCE>0.5</TERM_CONFIDENCE>
      <TERM_WEIGHTS>
            <WEIGHT name="CValue">1</WEIGHT>
            <WEIGHT name="CValue1">1.58496250072116</WEIGHT>
            <WEIGHT name="CValuePlus">1</WEIGHT>
            <WEIGHT name="CValuePlus1">1.58496250072116</WEIGHT>
            <WEIGHT name="CValueStar">N/A</WEIGHT>
            <WEIGHT name="CValueStarH">N/A</WEIGHT>
            <WEIGHT name="CValueStarM">N/A</WEIGHT>
            <WEIGHT name="CValueStarR">0.584962500721156</WEIGHT>
            <WEIGHT name="CValueWCard">0</WEIGHT>
            <WEIGHT name="CValueWCardPlus">0</WEIGHT>
            <WEIGHT name="D">1</WEIGHT>
            <WEIGHT name="DDW">0</WEIGHT>
            <WEIGHT name="Freq">1</WEIGHT>
            <WEIGHT name="IM">2</WEIGHT>
            <WEIGHT name="LLR">0.000115129154648748</WEIGHT>
            <WEIGHT name="NormFreq">0.5</WEIGHT>
            <WEIGHT name="iLong">0.5</WEIGHT>
            <WEIGHT name="iTer">0.333333333333333</WEIGHT>
            <WEIGHT name="idf">0:0</WEIGHT>
            <WEIGHT name="ilnc">0</WEIGHT>
            <WEIGHT name="ilncFreq">0</WEIGHT>
            <WEIGHT name="nbdoc4tc">1</WEIGHT>
            <WEIGHT name="tf">0:1</WEIGHT>
            <WEIGHT name="tf-idf">0:0</WEIGHT>
      </TERM_WEIGHTS>
      <LOG_INFORMATION>YaTeA</LOG_INFORMATION>
      <SYNTACTIC_ANALYSIS>
        <HEAD>
        term32
        </HEAD>
        <MODIFIER POSITION="AFTER">
        term33
        </MODIFIER>
      </SYNTACTIC_ANALYSIS>
    </TERM_CANDIDATE>
    <TERM_CANDIDATE MNP_STATUS="0">
      <ID>term14</ID>
      <FORM>périmètre</FORM>
      <LEMMA>périmètre</LEMMA>
      <MORPHOSYNTACTIC_FEATURES>
	    <SYNTACTIC_CATEGORY>NOM</SYNTACTIC_CATEGORY>
      </MORPHOSYNTACTIC_FEATURES>
      <HEAD>term14</HEAD>
      <NUMBER_OCCURRENCES>2</NUMBER_OCCURRENCES>
      <LIST_OCCURRENCES>
      <OCCURRENCE>
        <ID>occ32</ID>
        <MNP>0</MNP>
        <DOC>0</DOC>
        <SENTENCE>2</SENTENCE>
        <START_POSITION>3</START_POSITION>
        <END_POSITION>12</END_POSITION>
        </OCCURRENCE>
      <OCCURRENCE>
        <ID>occ58</ID>
        <MNP>0</MNP>
        <DOC>0</DOC>
        <SENTENCE>6</SENTENCE>
        <START_POSITION>49</START_POSITION>
        <END_POSITION>58</END_POSITION>
        </OCCURRENCE>
      </LIST_OCCURRENCES>
      <TERM_CONFIDENCE>0.5</TERM_CONFIDENCE>
      <TERM_WEIGHTS>
            <WEIGHT name="CValue">0</WEIGHT>
            <WEIGHT name="CValue1">0.5</WEIGHT>
            <WEIGHT name="CValuePlus">0</WEIGHT>
            <WEIGHT name="CValuePlus1">3.5</WEIGHT>
            <WEIGHT name="CValueStar">N/A</WEIGHT>
            <WEIGHT name="CValueStarH">-1</WEIGHT>
            <WEIGHT name="CValueStarM">N/A</WEIGHT>
            <WEIGHT name="CValueStarR">N/A</WEIGHT>
            <WEIGHT name="CValueWCard">0.5</WEIGHT>
            <WEIGHT name="CValueWCardPlus">3.5</WEIGHT>
            <WEIGHT name="D">1</WEIGHT>
            <WEIGHT name="DDW">0</WEIGHT>
            <WEIGHT name="Freq">2</WEIGHT>
            <WEIGHT name="IM">N/A</WEIGHT>
            <WEIGHT name="LLR">N/A</WEIGHT>
            <WEIGHT name="NormFreq">1</WEIGHT>
            <WEIGHT name="iLong">2</WEIGHT>
            <WEIGHT name="iTer">3</WEIGHT>
            <WEIGHT name="idf">0:0</WEIGHT>
            <WEIGHT name="ilnc">2</WEIGHT>
            <WEIGHT name="ilncFreq">3</WEIGHT>
            <WEIGHT name="nbdoc4tc">1</WEIGHT>
            <WEIGHT name="tf">0:2</WEIGHT>
            <WEIGHT name="tf-idf">0:0</WEIGHT>
      </TERM_WEIGHTS>
      <LOG_INFORMATION>YaTeA</LOG_INFORMATION>
    </TERM_CANDIDATE>
    <TERM_CANDIDATE MNP_STATUS="0">
      <ID>term33</ID>
      <FORM>électrique</FORM>
      <LEMMA>électrique</LEMMA>
      <MORPHOSYNTACTIC_FEATURES>
	    <SYNTACTIC_CATEGORY>ADJ</SYNTACTIC_CATEGORY>
      </MORPHOSYNTACTIC_FEATURES>
      <HEAD>term33</HEAD>
      <NUMBER_OCCURRENCES>1</NUMBER_OCCURRENCES>
      <LIST_OCCURRENCES>
      <OCCURRENCE>
        <ID>occ48</ID>
        <MNP>0</MNP>
        <DOC>0</DOC>
        <SENTENCE>5</SENTENCE>
        <START_POSITION>29</START_POSITION>
        <END_POSITION>39</END_POSITION>
        </OCCURRENCE>
      </LIST_OCCURRENCES>
      <TERM_CONFIDENCE>0.5</TERM_CONFIDENCE>
      <TERM_WEIGHTS>
            <WEIGHT name="CValue">0</WEIGHT>
            <WEIGHT name="CValue1">0</WEIGHT>
            <WEIGHT name="CValuePlus">0</WEIGHT>
            <WEIGHT name="CValuePlus1">2</WEIGHT>
            <WEIGHT name="CValueStar">N/A</WEIGHT>
            <WEIGHT name="CValueStarH">N/A</WEIGHT>
            <WEIGHT name="CValueStarM">0</WEIGHT>
            <WEIGHT name="CValueStarR">N/A</WEIGHT>
            <WEIGHT name="CValueWCard">0</WEIGHT>
            <WEIGHT name="CValueWCardPlus">2</WEIGHT>
            <WEIGHT name="D">1</WEIGHT>
            <WEIGHT name="DDW">0</WEIGHT>
            <WEIGHT name="Freq">1</WEIGHT>
            <WEIGHT name="IM">N/A</WEIGHT>
            <WEIGHT name="LLR">N/A</WEIGHT>
            <WEIGHT name="NormFreq">0.5</WEIGHT>
            <WEIGHT name="iLong">1</WEIGHT>
            <WEIGHT name="iTer">0.5</WEIGHT>
            <WEIGHT name="idf">0:0</WEIGHT>
            <WEIGHT name="ilnc">0</WEIGHT>
            <WEIGHT name="ilncFreq">0</WEIGHT>
            <WEIGHT name="nbdoc4tc">1</WEIGHT>
            <WEIGHT name="tf">0:1</WEIGHT>
            <WEIGHT name="tf-idf">0:0</WEIGHT>
      </TERM_WEIGHTS>
      <LOG_INFORMATION>YaTeA</LOG_INFORMATION>
    </TERM_CANDIDATE>
    <TERM_CANDIDATE MNP_STATUS="0">
      <ID>term11</ID>
      <FORM>moteur</FORM>
      <LEMMA>moteur</LEMMA>
      <MORPHOSYNTACTIC_FEATURES>
	    <SYNTACTIC_CATEGORY>ADJ</SYNTACTIC_CATEGORY>
      </MORPHOSYNTACTIC_FEATURES>
      <HEAD>term11</HEAD>
      <NUMBER_OCCURRENCES>1</NUMBER_OCCURRENCES>
      <LIST_OCCURRENCES>
      <OCCURRENCE>
        <ID>occ30</ID>
        <MNP>0</MNP>
        <DOC>0</DOC>
        <SENTENCE>0</SENTENCE>
        <START_POSITION>67</START_POSITION>
        <END_POSITION>73</END_POSITION>
        </OCCURRENCE>
      </LIST_OCCURRENCES>
      <TERM_CONFIDENCE>0.5</TERM_CONFIDENCE>
      <TERM_WEIGHTS>
            <WEIGHT name="CValue">0</WEIGHT>
            <WEIGHT name="CValue1">0</WEIGHT>
            <WEIGHT name="CValuePlus">0</WEIGHT>
            <WEIGHT name="CValuePlus1">2</WEIGHT>
            <WEIGHT name="CValueStar">N/A</WEIGHT>
            <WEIGHT name="CValueStarH">N/A</WEIGHT>
            <WEIGHT name="CValueStarM">0</WEIGHT>
            <WEIGHT name="CValueStarR">N/A</WEIGHT>
            <WEIGHT name="CValueWCard">0</WEIGHT>
            <WEIGHT name="CValueWCardPlus">2</WEIGHT>
            <WEIGHT name="D">1</WEIGHT>
            <WEIGHT name="DDW">0</WEIGHT>
            <WEIGHT name="Freq">1</WEIGHT>
            <WEIGHT name="IM">N/A</WEIGHT>
            <WEIGHT name="LLR">N/A</WEIGHT>
            <WEIGHT name="NormFreq">0.5</WEIGHT>
            <WEIGHT name="iLong">1</WEIGHT>
            <WEIGHT name="iTer">0.5</WEIGHT>
            <WEIGHT name="idf">0:0</WEIGHT>
            <WEIGHT name="ilnc">0</WEIGHT>
            <WEIGHT name="ilncFreq">0</WEIGHT>
            <WEIGHT name="nbdoc4tc">1</WEIGHT>
            <WEIGHT name="tf">0:1</WEIGHT>
            <WEIGHT name="tf-idf">0:0</WEIGHT>
      </TERM_WEIGHTS>
      <LOG_INFORMATION>YaTeA</LOG_INFORMATION>
    </TERM_CANDIDATE>
    <TERM_CANDIDATE MNP_STATUS="0">
      <ID>term24</ID>
      <FORM>éolienne</FORM>
      <LEMMA>éolienne</LEMMA>
      <MORPHOSYNTACTIC_FEATURES>
	    <SYNTACTIC_CATEGORY>NOM</SYNTACTIC_CATEGORY>
      </MORPHOSYNTACTIC_FEATURES>
      <HEAD>term24</HEAD>
      <NUMBER_OCCURRENCES>1</NUMBER_OCCURRENCES>
      <LIST_OCCURRENCES>
      <OCCURRENCE>
        <ID>occ40</ID>
        <MNP>0</MNP>
        <DOC>0</DOC>
        <SENTENCE>0</SENTENCE>
        <START_POSITION>81</START_POSITION>
        <END_POSITION>89</END_POSITION>
        </OCCURRENCE>
      </LIST_OCCURRENCES>
      <TERM_CONFIDENCE>0.5</TERM_CONFIDENCE>
      <TERM_WEIGHTS>
            <WEIGHT name="CValue">0</WEIGHT>
            <WEIGHT name="CValue1">0</WEIGHT>
            <WEIGHT name="CValuePlus">0</WEIGHT>
            <WEIGHT name="CValuePlus1">2</WEIGHT>
            <WEIGHT name="CValueStar">N/A</WEIGHT>
            <WEIGHT name="CValueStarH">0</WEIGHT>
            <WEIGHT name="CValueStarM">N/A</WEIGHT>
            <WEIGHT name="CValueStarR">N/A</WEIGHT>
            <WEIGHT name="CValueWCard">0</WEIGHT>
            <WEIGHT name="CValueWCardPlus">2</WEIGHT>
            <WEIGHT name="D">1</WEIGHT>
            <WEIGHT name="DDW">0</WEIGHT>
            <WEIGHT name="Freq">1</WEIGHT>
            <WEIGHT name="IM">N/A</WEIGHT>
            <WEIGHT name="LLR">N/A</WEIGHT>
            <WEIGHT name="NormFreq">0.5</WEIGHT>
            <WEIGHT name="iLong">1</WEIGHT>
            <WEIGHT name="iTer">1</WEIGHT>
            <WEIGHT name="idf">0:0</WEIGHT>
            <WEIGHT name="ilnc">1</WEIGHT>
            <WEIGHT name="ilncFreq">1</WEIGHT>
            <WEIGHT name="nbdoc4tc">1</WEIGHT>
            <WEIGHT name="tf">0:1</WEIGHT>
            <WEIGHT name="tf-idf">0:0</WEIGHT>
      </TERM_WEIGHTS>
      <LOG_INFORMATION>YaTeA</LOG_INFORMATION>
    </TERM_CANDIDATE>
    <TERM_CANDIDATE MNP_STATUS="0">
      <ID>term15</ID>
      <FORM>sécurité</FORM>
      <LEMMA>sécurité</LEMMA>
      <MORPHOSYNTACTIC_FEATURES>
	    <SYNTACTIC_CATEGORY>NOM</SYNTACTIC_CATEGORY>
      </MORPHOSYNTACTIC_FEATURES>
      <HEAD>term15</HEAD>
      <NUMBER_OCCURRENCES>2</NUMBER_OCCURRENCES>
      <LIST_OCCURRENCES>
      <OCCURRENCE>
        <ID>occ33</ID>
        <MNP>0</MNP>
        <DOC>0</DOC>
        <SENTENCE>2</SENTENCE>
        <START_POSITION>16</START_POSITION>
        <END_POSITION>24</END_POSITION>
        </OCCURRENCE>
      <OCCURRENCE>
        <ID>occ59</ID>
        <MNP>0</MNP>
        <DOC>0</DOC>
        <SENTENCE>6</SENTENCE>
        <START_POSITION>62</START_POSITION>
        <END_POSITION>70</END_POSITION>
        </OCCURRENCE>
      </LIST_OCCURRENCES>
      <TERM_CONFIDENCE>0.5</TERM_CONFIDENCE>
      <TERM_WEIGHTS>
            <WEIGHT name="CValue">0</WEIGHT>
            <WEIGHT name="CValue1">0.5</WEIGHT>
            <WEIGHT name="CValuePlus">0</WEIGHT>
            <WEIGHT name="CValuePlus1">3.5</WEIGHT>
            <WEIGHT name="CValueStar">N/A</WEIGHT>
            <WEIGHT name="CValueStarH">N/A</WEIGHT>
            <WEIGHT name="CValueStarM">-1</WEIGHT>
            <WEIGHT name="CValueStarR">N/A</WEIGHT>
            <WEIGHT name="CValueWCard">0.5</WEIGHT>
            <WEIGHT name="CValueWCardPlus">3.5</WEIGHT>
            <WEIGHT name="D">1</WEIGHT>
            <WEIGHT name="DDW">0</WEIGHT>
            <WEIGHT name="Freq">2</WEIGHT>
            <WEIGHT name="IM">N/A</WEIGHT>
            <WEIGHT name="LLR">N/A</WEIGHT>
            <WEIGHT name="NormFreq">1</WEIGHT>
            <WEIGHT name="iLong">2</WEIGHT>
            <WEIGHT name="iTer">1</WEIGHT>
            <WEIGHT name="idf">0:0</WEIGHT>
            <WEIGHT name="ilnc">0</WEIGHT>
            <WEIGHT name="ilncFreq">0</WEIGHT>
            <WEIGHT name="nbdoc4tc">1</WEIGHT>
            <WEIGHT name="tf">0:2</WEIGHT>
            <WEIGHT name="tf-idf">0:0</WEIGHT>
      </TERM_WEIGHTS>
      <LOG_INFORMATION>YaTeA</LOG_INFORMATION>
    </TERM_CANDIDATE>
    <TERM_CANDIDATE MNP_STATUS="0">
      <ID>term3</ID>
      <FORM>feu.L&apos;éolienne sinistrée</FORM>
      <LEMMA>feu.L&apos;éolienne sinistré</LEMMA>
      <MORPHOSYNTACTIC_FEATURES>
	    <SYNTACTIC_CATEGORY>NOM ADJ</SYNTACTIC_CATEGORY>
      </MORPHOSYNTACTIC_FEATURES>
      <HEAD>term4</HEAD>
      <NUMBER_OCCURRENCES>1</NUMBER_OCCURRENCES>
      <LIST_OCCURRENCES>
      <OCCURRENCE>
        <ID>occ24</ID>
        <MNP>0</MNP>
        <DOC>0</DOC>
        <SENTENCE>5</SENTENCE>
        <START_POSITION>68</START_POSITION>
        <END_POSITION>92</END_POSITION>
        </OCCURRENCE>
      </LIST_OCCURRENCES>
      <TERM_CONFIDENCE>0.5</TERM_CONFIDENCE>
      <TERM_WEIGHTS>
            <WEIGHT name="CValue">0</WEIGHT>
            <WEIGHT name="CValue1">0</WEIGHT>
            <WEIGHT name="CValuePlus">2</WEIGHT>
            <WEIGHT name="CValuePlus1">3.16992500144231</WEIGHT>
            <WEIGHT name="CValueStar">N/A</WEIGHT>
            <WEIGHT name="CValueStarH">N/A</WEIGHT>
            <WEIGHT name="CValueStarM">0</WEIGHT>
            <WEIGHT name="CValueStarR">N/A</WEIGHT>
            <WEIGHT name="CValueWCard">0</WEIGHT>
            <WEIGHT name="CValueWCardPlus">2</WEIGHT>
            <WEIGHT name="D">1</WEIGHT>
            <WEIGHT name="DDW">0</WEIGHT>
            <WEIGHT name="Freq">1</WEIGHT>
            <WEIGHT name="IM">2</WEIGHT>
            <WEIGHT name="LLR">0.000115129154648748</WEIGHT>
            <WEIGHT name="NormFreq">0.5</WEIGHT>
            <WEIGHT name="iLong">0.5</WEIGHT>
            <WEIGHT name="iTer">0.333333333333333</WEIGHT>
            <WEIGHT name="idf">0:0</WEIGHT>
            <WEIGHT name="ilnc">0</WEIGHT>
            <WEIGHT name="ilncFreq">0</WEIGHT>
            <WEIGHT name="nbdoc4tc">1</WEIGHT>
            <WEIGHT name="tf">0:1</WEIGHT>
            <WEIGHT name="tf-idf">0:0</WEIGHT>
      </TERM_WEIGHTS>
      <LOG_INFORMATION>YaTeA</LOG_INFORMATION>
      <SYNTACTIC_ANALYSIS>
        <HEAD>
        term4
        </HEAD>
        <MODIFIER POSITION="AFTER">
        term5
        </MODIFIER>
      </SYNTACTIC_ANALYSIS>
    </TERM_CANDIDATE>
    <TERM_CANDIDATE MNP_STATUS="1">
      <ID>term13</ID>
      <FORM>périmètre de sécurité</FORM>
      <LEMMA>périmètre de sécurité</LEMMA>
      <MORPHOSYNTACTIC_FEATURES>
	    <SYNTACTIC_CATEGORY>NOM de NOM</SYNTACTIC_CATEGORY>
      </MORPHOSYNTACTIC_FEATURES>
      <HEAD>term14</HEAD>
      <NUMBER_OCCURRENCES>2</NUMBER_OCCURRENCES>
      <LIST_OCCURRENCES>
      <OCCURRENCE>
        <ID>occ31</ID>
        <MNP>0</MNP>
        <DOC>0</DOC>
        <SENTENCE>2</SENTENCE>
        <START_POSITION>3</START_POSITION>
        <END_POSITION>24</END_POSITION>
        </OCCURRENCE>
      <OCCURRENCE>
        <ID>occ20</ID>
        <MNP>1</MNP>
        <DOC>0</DOC>
        <SENTENCE>6</SENTENCE>
        <START_POSITION>49</START_POSITION>
        <END_POSITION>70</END_POSITION>
        </OCCURRENCE>
      </LIST_OCCURRENCES>
      <TERM_CONFIDENCE>0.5</TERM_CONFIDENCE>
      <TERM_WEIGHTS>
            <WEIGHT name="CValue">1.58496250072116</WEIGHT>
            <WEIGHT name="CValue1">2</WEIGHT>
            <WEIGHT name="CValuePlus">4.75488750216347</WEIGHT>
            <WEIGHT name="CValuePlus1">6</WEIGHT>
            <WEIGHT name="CValueStar">N/A</WEIGHT>
            <WEIGHT name="CValueStarH">0.415037499278844</WEIGHT>
            <WEIGHT name="CValueStarM">N/A</WEIGHT>
            <WEIGHT name="CValueStarR">N/A</WEIGHT>
            <WEIGHT name="CValueWCard">1</WEIGHT>
            <WEIGHT name="CValueWCardPlus">3</WEIGHT>
            <WEIGHT name="D">1</WEIGHT>
            <WEIGHT name="DDW">0</WEIGHT>
            <WEIGHT name="Freq">2</WEIGHT>
            <WEIGHT name="IM">1</WEIGHT>
            <WEIGHT name="LLR">1.09859895531206e-05</WEIGHT>
            <WEIGHT name="NormFreq">1</WEIGHT>
            <WEIGHT name="iLong">0.666666666666667</WEIGHT>
            <WEIGHT name="iTer">1</WEIGHT>
            <WEIGHT name="idf">0:0</WEIGHT>
            <WEIGHT name="ilnc">1</WEIGHT>
            <WEIGHT name="ilncFreq">1</WEIGHT>
            <WEIGHT name="nbdoc4tc">1</WEIGHT>
            <WEIGHT name="tf">0:2</WEIGHT>
            <WEIGHT name="tf-idf">0:0</WEIGHT>
      </TERM_WEIGHTS>
      <LOG_INFORMATION>YaTeA</LOG_INFORMATION>
      <SYNTACTIC_ANALYSIS>
        <HEAD>
        term14
        </HEAD>
        <MODIFIER POSITION="AFTER">
        term15
        </MODIFIER>
        <PREP>
        de
        </PREP>
      </SYNTACTIC_ANALYSIS>
    </TERM_CANDIDATE>
    <TERM_CANDIDATE MNP_STATUS="0">
      <ID>term17</ID>
      <FORM>300</FORM>
      <LEMMA>300</LEMMA>
      <MORPHOSYNTACTIC_FEATURES>
	    <SYNTACTIC_CATEGORY>NUM</SYNTACTIC_CATEGORY>
      </MORPHOSYNTACTIC_FEATURES>
      <HEAD>term17</HEAD>
      <NUMBER_OCCURRENCES>1</NUMBER_OCCURRENCES>
      <LIST_OCCURRENCES>
      <OCCURRENCE>
        <ID>occ35</ID>
        <MNP>0</MNP>
        <DOC>0</DOC>
        <SENTENCE>2</SENTENCE>
        <START_POSITION>28</START_POSITION>
        <END_POSITION>31</END_POSITION>
        </OCCURRENCE>
      </LIST_OCCURRENCES>
      <TERM_CONFIDENCE>0.5</TERM_CONFIDENCE>
      <TERM_WEIGHTS>
            <WEIGHT name="CValue">0</WEIGHT>
            <WEIGHT name="CValue1">0</WEIGHT>
            <WEIGHT name="CValuePlus">0</WEIGHT>
            <WEIGHT name="CValuePlus1">2</WEIGHT>
            <WEIGHT name="CValueStar">N/A</WEIGHT>
            <WEIGHT name="CValueStarH">N/A</WEIGHT>
            <WEIGHT name="CValueStarM">0</WEIGHT>
            <WEIGHT name="CValueStarR">N/A</WEIGHT>
            <WEIGHT name="CValueWCard">0</WEIGHT>
            <WEIGHT name="CValueWCardPlus">2</WEIGHT>
            <WEIGHT name="D">1</WEIGHT>
            <WEIGHT name="DDW">0</WEIGHT>
            <WEIGHT name="Freq">1</WEIGHT>
            <WEIGHT name="IM">N/A</WEIGHT>
            <WEIGHT name="LLR">N/A</WEIGHT>
            <WEIGHT name="NormFreq">0.5</WEIGHT>
            <WEIGHT name="iLong">1</WEIGHT>
            <WEIGHT name="iTer">0.5</WEIGHT>
            <WEIGHT name="idf">0:0</WEIGHT>
            <WEIGHT name="ilnc">0</WEIGHT>
            <WEIGHT name="ilncFreq">0</WEIGHT>
            <WEIGHT name="nbdoc4tc">1</WEIGHT>
            <WEIGHT name="tf">0:1</WEIGHT>
            <WEIGHT name="tf-idf">0:0</WEIGHT>
      </TERM_WEIGHTS>
      <LOG_INFORMATION>YaTeA</LOG_INFORMATION>
    </TERM_CANDIDATE>
    <TERM_CANDIDATE MNP_STATUS="1">
      <ID>term29</ID>
      <FORM>mise</FORM>
      <LEMMA>mise</LEMMA>
      <MORPHOSYNTACTIC_FEATURES>
	    <SYNTACTIC_CATEGORY>NOM</SYNTACTIC_CATEGORY>
      </MORPHOSYNTACTIC_FEATURES>
      <HEAD>term29</HEAD>
      <NUMBER_OCCURRENCES>1</NUMBER_OCCURRENCES>
      <LIST_OCCURRENCES>
      <OCCURRENCE>
        <ID>occ45</ID>
        <MNP>1</MNP>
        <DOC>0</DOC>
        <SENTENCE>6</SENTENCE>
        <START_POSITION>29</START_POSITION>
        <END_POSITION>33</END_POSITION>
        </OCCURRENCE>
      </LIST_OCCURRENCES>
      <TERM_CONFIDENCE>0.5</TERM_CONFIDENCE>
      <TERM_WEIGHTS>
            <WEIGHT name="CValue">0</WEIGHT>
            <WEIGHT name="CValue1">1</WEIGHT>
            <WEIGHT name="CValuePlus">0</WEIGHT>
            <WEIGHT name="CValuePlus1">1</WEIGHT>
            <WEIGHT name="CValueStar">N/A</WEIGHT>
            <WEIGHT name="CValueStarH">N/A</WEIGHT>
            <WEIGHT name="CValueStarM">N/A</WEIGHT>
            <WEIGHT name="CValueStarR">1</WEIGHT>
            <WEIGHT name="CValueWCard">0</WEIGHT>
            <WEIGHT name="CValueWCardPlus">0</WEIGHT>
            <WEIGHT name="D">1</WEIGHT>
            <WEIGHT name="DDW">0</WEIGHT>
            <WEIGHT name="Freq">1</WEIGHT>
            <WEIGHT name="IM">N/A</WEIGHT>
            <WEIGHT name="LLR">N/A</WEIGHT>
            <WEIGHT name="NormFreq">0.5</WEIGHT>
            <WEIGHT name="iLong">1</WEIGHT>
            <WEIGHT name="iTer">0.5</WEIGHT>
            <WEIGHT name="idf">0:0</WEIGHT>
            <WEIGHT name="ilnc">0</WEIGHT>
            <WEIGHT name="ilncFreq">0</WEIGHT>
            <WEIGHT name="nbdoc4tc">1</WEIGHT>
            <WEIGHT name="tf">0:1</WEIGHT>
            <WEIGHT name="tf-idf">0:0</WEIGHT>
      </TERM_WEIGHTS>
      <LOG_INFORMATION>YaTeA</LOG_INFORMATION>
    </TERM_CANDIDATE>
    <TERM_CANDIDATE MNP_STATUS="0">
      <ID>term8</ID>
      <FORM>aéronautique</FORM>
      <LEMMA>aéronautique</LEMMA>
      <MORPHOSYNTACTIC_FEATURES>
	    <SYNTACTIC_CATEGORY>ADJ</SYNTACTIC_CATEGORY>
      </MORPHOSYNTACTIC_FEATURES>
      <HEAD>term8</HEAD>
      <NUMBER_OCCURRENCES>1</NUMBER_OCCURRENCES>
      <LIST_OCCURRENCES>
      <OCCURRENCE>
        <ID>occ28</ID>
        <MNP>0</MNP>
        <DOC>0</DOC>
        <SENTENCE>4</SENTENCE>
        <START_POSITION>12</START_POSITION>
        <END_POSITION>24</END_POSITION>
        </OCCURRENCE>
      </LIST_OCCURRENCES>
      <TERM_CONFIDENCE>0.5</TERM_CONFIDENCE>
      <TERM_WEIGHTS>
            <WEIGHT name="CValue">0</WEIGHT>
            <WEIGHT name="CValue1">0</WEIGHT>
            <WEIGHT name="CValuePlus">0</WEIGHT>
            <WEIGHT name="CValuePlus1">2</WEIGHT>
            <WEIGHT name="CValueStar">N/A</WEIGHT>
            <WEIGHT name="CValueStarH">N/A</WEIGHT>
            <WEIGHT name="CValueStarM">0</WEIGHT>
            <WEIGHT name="CValueStarR">N/A</WEIGHT>
            <WEIGHT name="CValueWCard">0</WEIGHT>
            <WEIGHT name="CValueWCardPlus">2</WEIGHT>
            <WEIGHT name="D">1</WEIGHT>
            <WEIGHT name="DDW">0</WEIGHT>
            <WEIGHT name="Freq">1</WEIGHT>
            <WEIGHT name="IM">N/A</WEIGHT>
            <WEIGHT name="LLR">N/A</WEIGHT>
            <WEIGHT name="NormFreq">0.5</WEIGHT>
            <WEIGHT name="iLong">1</WEIGHT>
            <WEIGHT name="iTer">0.5</WEIGHT>
            <WEIGHT name="idf">0:0</WEIGHT>
            <WEIGHT name="ilnc">0</WEIGHT>
            <WEIGHT name="ilncFreq">0</WEIGHT>
            <WEIGHT name="nbdoc4tc">1</WEIGHT>
            <WEIGHT name="tf">0:1</WEIGHT>
            <WEIGHT name="tf-idf">0:0</WEIGHT>
      </TERM_WEIGHTS>
      <LOG_INFORMATION>YaTeA</LOG_INFORMATION>
    </TERM_CANDIDATE>
    <TERM_CANDIDATE MNP_STATUS="0">
      <ID>term40</ID>
      <FORM>services</FORM>
      <LEMMA>service</LEMMA>
      <MORPHOSYNTACTIC_FEATURES>
	    <SYNTACTIC_CATEGORY>NOM</SYNTACTIC_CATEGORY>
      </MORPHOSYNTACTIC_FEATURES>
      <HEAD>term40</HEAD>
      <NUMBER_OCCURRENCES>1</NUMBER_OCCURRENCES>
      <LIST_OCCURRENCES>
      <OCCURRENCE>
        <ID>occ53</ID>
        <MNP>0</MNP>
        <DOC>0</DOC>
        <SENTENCE>4</SENTENCE>
        <START_POSITION>64</START_POSITION>
        <END_POSITION>72</END_POSITION>
        </OCCURRENCE>
      </LIST_OCCURRENCES>
      <TERM_CONFIDENCE>0.5</TERM_CONFIDENCE>
      <TERM_WEIGHTS>
            <WEIGHT name="CValue">0</WEIGHT>
            <WEIGHT name="CValue1">0</WEIGHT>
            <WEIGHT name="CValuePlus">0</WEIGHT>
            <WEIGHT name="CValuePlus1">2</WEIGHT>
            <WEIGHT name="CValueStar">N/A</WEIGHT>
            <WEIGHT name="CValueStarH">0</WEIGHT>
            <WEIGHT name="CValueStarM">N/A</WEIGHT>
            <WEIGHT name="CValueStarR">N/A</WEIGHT>
            <WEIGHT name="CValueWCard">0</WEIGHT>
            <WEIGHT name="CValueWCardPlus">2</WEIGHT>
            <WEIGHT name="D">1</WEIGHT>
            <WEIGHT name="DDW">0</WEIGHT>
            <WEIGHT name="Freq">1</WEIGHT>
            <WEIGHT name="IM">N/A</WEIGHT>
            <WEIGHT name="LLR">N/A</WEIGHT>
            <WEIGHT name="NormFreq">0.5</WEIGHT>
            <WEIGHT name="iLong">1</WEIGHT>
            <WEIGHT name="iTer">1</WEIGHT>
            <WEIGHT name="idf">0:0</WEIGHT>
            <WEIGHT name="ilnc">1</WEIGHT>
            <WEIGHT name="ilncFreq">1</WEIGHT>
            <WEIGHT name="nbdoc4tc">1</WEIGHT>
            <WEIGHT name="tf">0:1</WEIGHT>
            <WEIGHT name="tf-idf">0:0</WEIGHT>
      </TERM_WEIGHTS>
      <LOG_INFORMATION>YaTeA</LOG_INFORMATION>
    </TERM_CANDIDATE>
    <TERM_CANDIDATE MNP_STATUS="0">
      <ID>term10</ID>
      <FORM>partie</FORM>
      <LEMMA>partie</LEMMA>
      <MORPHOSYNTACTIC_FEATURES>
	    <SYNTACTIC_CATEGORY>NOM</SYNTACTIC_CATEGORY>
      </MORPHOSYNTACTIC_FEATURES>
      <HEAD>term10</HEAD>
      <NUMBER_OCCURRENCES>1</NUMBER_OCCURRENCES>
      <LIST_OCCURRENCES>
      <OCCURRENCE>
        <ID>occ29</ID>
        <MNP>0</MNP>
        <DOC>0</DOC>
        <SENTENCE>0</SENTENCE>
        <START_POSITION>60</START_POSITION>
        <END_POSITION>66</END_POSITION>
        </OCCURRENCE>
      </LIST_OCCURRENCES>
      <TERM_CONFIDENCE>0.5</TERM_CONFIDENCE>
      <TERM_WEIGHTS>
            <WEIGHT name="CValue">0</WEIGHT>
            <WEIGHT name="CValue1">0</WEIGHT>
            <WEIGHT name="CValuePlus">0</WEIGHT>
            <WEIGHT name="CValuePlus1">2</WEIGHT>
            <WEIGHT name="CValueStar">N/A</WEIGHT>
            <WEIGHT name="CValueStarH">0</WEIGHT>
            <WEIGHT name="CValueStarM">N/A</WEIGHT>
            <WEIGHT name="CValueStarR">N/A</WEIGHT>
            <WEIGHT name="CValueWCard">0</WEIGHT>
            <WEIGHT name="CValueWCardPlus">2</WEIGHT>
            <WEIGHT name="D">1</WEIGHT>
            <WEIGHT name="DDW">0</WEIGHT>
            <WEIGHT name="Freq">1</WEIGHT>
            <WEIGHT name="IM">N/A</WEIGHT>
            <WEIGHT name="LLR">N/A</WEIGHT>
            <WEIGHT name="NormFreq">0.5</WEIGHT>
            <WEIGHT name="iLong">1</WEIGHT>
            <WEIGHT name="iTer">1</WEIGHT>
            <WEIGHT name="idf">0:0</WEIGHT>
            <WEIGHT name="ilnc">1</WEIGHT>
            <WEIGHT name="ilncFreq">1</WEIGHT>
            <WEIGHT name="nbdoc4tc">1</WEIGHT>
            <WEIGHT name="tf">0:1</WEIGHT>
            <WEIGHT name="tf-idf">0:0</WEIGHT>
      </TERM_WEIGHTS>
      <LOG_INFORMATION>YaTeA</LOG_INFORMATION>
    </TERM_CANDIDATE>
    <TERM_CANDIDATE MNP_STATUS="1">
      <ID>term6</ID>
      <FORM>balisage aéronautique</FORM>
      <LEMMA>balisage aéronautique</LEMMA>
      <MORPHOSYNTACTIC_FEATURES>
	    <SYNTACTIC_CATEGORY>NOM ADJ</SYNTACTIC_CATEGORY>
      </MORPHOSYNTACTIC_FEATURES>
      <HEAD>term7</HEAD>
      <NUMBER_OCCURRENCES>1</NUMBER_OCCURRENCES>
      <LIST_OCCURRENCES>
      <OCCURRENCE>
        <ID>occ10</ID>
        <MNP>1</MNP>
        <DOC>0</DOC>
        <SENTENCE>4</SENTENCE>
        <START_POSITION>3</START_POSITION>
        <END_POSITION>24</END_POSITION>
        </OCCURRENCE>
      </LIST_OCCURRENCES>
      <TERM_CONFIDENCE>0.5</TERM_CONFIDENCE>
      <TERM_WEIGHTS>
            <WEIGHT name="CValue">1</WEIGHT>
            <WEIGHT name="CValue1">1.58496250072116</WEIGHT>
            <WEIGHT name="CValuePlus">1</WEIGHT>
            <WEIGHT name="CValuePlus1">1.58496250072116</WEIGHT>
            <WEIGHT name="CValueStar">N/A</WEIGHT>
            <WEIGHT name="CValueStarH">N/A</WEIGHT>
            <WEIGHT name="CValueStarM">N/A</WEIGHT>
            <WEIGHT name="CValueStarR">0.584962500721156</WEIGHT>
            <WEIGHT name="CValueWCard">0</WEIGHT>
            <WEIGHT name="CValueWCardPlus">0</WEIGHT>
            <WEIGHT name="D">1</WEIGHT>
            <WEIGHT name="DDW">0</WEIGHT>
            <WEIGHT name="Freq">1</WEIGHT>
            <WEIGHT name="IM">2</WEIGHT>
            <WEIGHT name="LLR">0.000115129154648748</WEIGHT>
            <WEIGHT name="NormFreq">0.5</WEIGHT>
            <WEIGHT name="iLong">0.5</WEIGHT>
            <WEIGHT name="iTer">0.333333333333333</WEIGHT>
            <WEIGHT name="idf">0:0</WEIGHT>
            <WEIGHT name="ilnc">0</WEIGHT>
            <WEIGHT name="ilncFreq">0</WEIGHT>
            <WEIGHT name="nbdoc4tc">1</WEIGHT>
            <WEIGHT name="tf">0:1</WEIGHT>
            <WEIGHT name="tf-idf">0:0</WEIGHT>
      </TERM_WEIGHTS>
      <LOG_INFORMATION>YaTeA</LOG_INFORMATION>
      <SYNTACTIC_ANALYSIS>
        <HEAD>
        term7
        </HEAD>
        <MODIFIER POSITION="AFTER">
        term8
        </MODIFIER>
      </SYNTACTIC_ANALYSIS>
    </TERM_CANDIDATE>
    <TERM_CANDIDATE MNP_STATUS="1">
      <ID>term28</ID>
      <FORM>rotor</FORM>
      <LEMMA>rotor</LEMMA>
      <MORPHOSYNTACTIC_FEATURES>
	    <SYNTACTIC_CATEGORY>NOM</SYNTACTIC_CATEGORY>
      </MORPHOSYNTACTIC_FEATURES>
      <HEAD>term28</HEAD>
      <NUMBER_OCCURRENCES>1</NUMBER_OCCURRENCES>
      <LIST_OCCURRENCES>
      <OCCURRENCE>
        <ID>occ44</ID>
        <MNP>1</MNP>
        <DOC>0</DOC>
        <SENTENCE>3</SENTENCE>
        <START_POSITION>68</START_POSITION>
        <END_POSITION>73</END_POSITION>
        </OCCURRENCE>
      </LIST_OCCURRENCES>
      <TERM_CONFIDENCE>0.5</TERM_CONFIDENCE>
      <TERM_WEIGHTS>
            <WEIGHT name="CValue">0</WEIGHT>
            <WEIGHT name="CValue1">1</WEIGHT>
            <WEIGHT name="CValuePlus">0</WEIGHT>
            <WEIGHT name="CValuePlus1">1</WEIGHT>
            <WEIGHT name="CValueStar">N/A</WEIGHT>
            <WEIGHT name="CValueStarH">N/A</WEIGHT>
            <WEIGHT name="CValueStarM">N/A</WEIGHT>
            <WEIGHT name="CValueStarR">1</WEIGHT>
            <WEIGHT name="CValueWCard">0</WEIGHT>
            <WEIGHT name="CValueWCardPlus">0</WEIGHT>
            <WEIGHT name="D">1</WEIGHT>
            <WEIGHT name="DDW">0</WEIGHT>
            <WEIGHT name="Freq">1</WEIGHT>
            <WEIGHT name="IM">N/A</WEIGHT>
            <WEIGHT name="LLR">N/A</WEIGHT>
            <WEIGHT name="NormFreq">0.5</WEIGHT>
            <WEIGHT name="iLong">1</WEIGHT>
            <WEIGHT name="iTer">0.5</WEIGHT>
            <WEIGHT name="idf">0:0</WEIGHT>
            <WEIGHT name="ilnc">0</WEIGHT>
            <WEIGHT name="ilncFreq">0</WEIGHT>
            <WEIGHT name="nbdoc4tc">1</WEIGHT>
            <WEIGHT name="tf">0:1</WEIGHT>
            <WEIGHT name="tf-idf">0:0</WEIGHT>
      </TERM_WEIGHTS>
      <LOG_INFORMATION>YaTeA</LOG_INFORMATION>
    </TERM_CANDIDATE>
    <TERM_CANDIDATE MNP_STATUS="0">
      <ID>term4</ID>
      <FORM>feu.L&apos;éolienne</FORM>
      <LEMMA>feu.L&apos;éolienne</LEMMA>
      <MORPHOSYNTACTIC_FEATURES>
	    <SYNTACTIC_CATEGORY>NOM</SYNTACTIC_CATEGORY>
      </MORPHOSYNTACTIC_FEATURES>
      <HEAD>term4</HEAD>
      <NUMBER_OCCURRENCES>1</NUMBER_OCCURRENCES>
      <LIST_OCCURRENCES>
      <OCCURRENCE>
        <ID>occ25</ID>
        <MNP>0</MNP>
        <DOC>0</DOC>
        <SENTENCE>5</SENTENCE>
        <START_POSITION>68</START_POSITION>
        <END_POSITION>82</END_POSITION>
        </OCCURRENCE>
      </LIST_OCCURRENCES>
      <TERM_CONFIDENCE>0.5</TERM_CONFIDENCE>
      <TERM_WEIGHTS>
            <WEIGHT name="CValue">0</WEIGHT>
            <WEIGHT name="CValue1">0</WEIGHT>
            <WEIGHT name="CValuePlus">0</WEIGHT>
            <WEIGHT name="CValuePlus1">2</WEIGHT>
            <WEIGHT name="CValueStar">N/A</WEIGHT>
            <WEIGHT name="CValueStarH">0</WEIGHT>
            <WEIGHT name="CValueStarM">N/A</WEIGHT>
            <WEIGHT name="CValueStarR">N/A</WEIGHT>
            <WEIGHT name="CValueWCard">0</WEIGHT>
            <WEIGHT name="CValueWCardPlus">2</WEIGHT>
            <WEIGHT name="D">1</WEIGHT>
            <WEIGHT name="DDW">0</WEIGHT>
            <WEIGHT name="Freq">1</WEIGHT>
            <WEIGHT name="IM">N/A</WEIGHT>
            <WEIGHT name="LLR">N/A</WEIGHT>
            <WEIGHT name="NormFreq">0.5</WEIGHT>
            <WEIGHT name="iLong">1</WEIGHT>
            <WEIGHT name="iTer">1</WEIGHT>
            <WEIGHT name="idf">0:0</WEIGHT>
            <WEIGHT name="ilnc">1</WEIGHT>
            <WEIGHT name="ilncFreq">1</WEIGHT>
            <WEIGHT name="nbdoc4tc">1</WEIGHT>
            <WEIGHT name="tf">0:1</WEIGHT>
            <WEIGHT name="tf-idf">0:0</WEIGHT>
      </TERM_WEIGHTS>
      <LOG_INFORMATION>YaTeA</LOG_INFORMATION>
    </TERM_CANDIDATE>
    <TERM_CANDIDATE MNP_STATUS="0">
      <ID>term43</ID>
      <FORM>civile</FORM>
      <LEMMA>civil</LEMMA>
      <MORPHOSYNTACTIC_FEATURES>
	    <SYNTACTIC_CATEGORY>ADJ</SYNTACTIC_CATEGORY>
      </MORPHOSYNTACTIC_FEATURES>
      <HEAD>term43</HEAD>
      <NUMBER_OCCURRENCES>1</NUMBER_OCCURRENCES>
      <LIST_OCCURRENCES>
      <OCCURRENCE>
        <ID>occ56</ID>
        <MNP>0</MNP>
        <DOC>0</DOC>
        <SENTENCE>4</SENTENCE>
        <START_POSITION>88</START_POSITION>
        <END_POSITION>94</END_POSITION>
        </OCCURRENCE>
      </LIST_OCCURRENCES>
      <TERM_CONFIDENCE>0.5</TERM_CONFIDENCE>
      <TERM_WEIGHTS>
            <WEIGHT name="CValue">0</WEIGHT>
            <WEIGHT name="CValue1">0</WEIGHT>
            <WEIGHT name="CValuePlus">0</WEIGHT>
            <WEIGHT name="CValuePlus1">2</WEIGHT>
            <WEIGHT name="CValueStar">N/A</WEIGHT>
            <WEIGHT name="CValueStarH">N/A</WEIGHT>
            <WEIGHT name="CValueStarM">0</WEIGHT>
            <WEIGHT name="CValueStarR">N/A</WEIGHT>
            <WEIGHT name="CValueWCard">0</WEIGHT>
            <WEIGHT name="CValueWCardPlus">2</WEIGHT>
            <WEIGHT name="D">1</WEIGHT>
            <WEIGHT name="DDW">0</WEIGHT>
            <WEIGHT name="Freq">1</WEIGHT>
            <WEIGHT name="IM">N/A</WEIGHT>
            <WEIGHT name="LLR">N/A</WEIGHT>
            <WEIGHT name="NormFreq">0.5</WEIGHT>
            <WEIGHT name="iLong">1</WEIGHT>
            <WEIGHT name="iTer">0.5</WEIGHT>
            <WEIGHT name="idf">0:0</WEIGHT>
            <WEIGHT name="ilnc">0</WEIGHT>
            <WEIGHT name="ilncFreq">0</WEIGHT>
            <WEIGHT name="nbdoc4tc">1</WEIGHT>
            <WEIGHT name="tf">0:1</WEIGHT>
            <WEIGHT name="tf-idf">0:0</WEIGHT>
      </TERM_WEIGHTS>
      <LOG_INFORMATION>YaTeA</LOG_INFORMATION>
    </TERM_CANDIDATE>
    <TERM_CANDIDATE MNP_STATUS="1">
      <ID>term44</ID>
      <FORM>nacelle</FORM>
      <LEMMA>nacelle</LEMMA>
      <MORPHOSYNTACTIC_FEATURES>
	    <SYNTACTIC_CATEGORY>NOM</SYNTACTIC_CATEGORY>
      </MORPHOSYNTACTIC_FEATURES>
      <HEAD>term44</HEAD>
      <NUMBER_OCCURRENCES>1</NUMBER_OCCURRENCES>
      <LIST_OCCURRENCES>
      <OCCURRENCE>
        <ID>occ57</ID>
        <MNP>1</MNP>
        <DOC>0</DOC>
        <SENTENCE>3</SENTENCE>
        <START_POSITION>42</START_POSITION>
        <END_POSITION>49</END_POSITION>
        </OCCURRENCE>
      </LIST_OCCURRENCES>
      <TERM_CONFIDENCE>0.5</TERM_CONFIDENCE>
      <TERM_WEIGHTS>
            <WEIGHT name="CValue">0</WEIGHT>
            <WEIGHT name="CValue1">1</WEIGHT>
            <WEIGHT name="CValuePlus">0</WEIGHT>
            <WEIGHT name="CValuePlus1">1</WEIGHT>
            <WEIGHT name="CValueStar">N/A</WEIGHT>
            <WEIGHT name="CValueStarH">N/A</WEIGHT>
            <WEIGHT name="CValueStarM">N/A</WEIGHT>
            <WEIGHT name="CValueStarR">1</WEIGHT>
            <WEIGHT name="CValueWCard">0</WEIGHT>
            <WEIGHT name="CValueWCardPlus">0</WEIGHT>
            <WEIGHT name="D">1</WEIGHT>
            <WEIGHT name="DDW">0</WEIGHT>
            <WEIGHT name="Freq">1</WEIGHT>
            <WEIGHT name="IM">N/A</WEIGHT>
            <WEIGHT name="LLR">N/A</WEIGHT>
            <WEIGHT name="NormFreq">0.5</WEIGHT>
            <WEIGHT name="iLong">1</WEIGHT>
            <WEIGHT name="iTer">0.5</WEIGHT>
            <WEIGHT name="idf">0:0</WEIGHT>
            <WEIGHT name="ilnc">0</WEIGHT>
            <WEIGHT name="ilncFreq">0</WEIGHT>
            <WEIGHT name="nbdoc4tc">1</WEIGHT>
            <WEIGHT name="tf">0:1</WEIGHT>
            <WEIGHT name="tf-idf">0:0</WEIGHT>
      </TERM_WEIGHTS>
      <LOG_INFORMATION>YaTeA</LOG_INFORMATION>
    </TERM_CANDIDATE>
    <TERM_CANDIDATE MNP_STATUS="0">
      <ID>term18</ID>
      <FORM>m</FORM>
      <LEMMA>m</LEMMA>
      <MORPHOSYNTACTIC_FEATURES>
	    <SYNTACTIC_CATEGORY>NOM</SYNTACTIC_CATEGORY>
      </MORPHOSYNTACTIC_FEATURES>
      <HEAD>term18</HEAD>
      <NUMBER_OCCURRENCES>1</NUMBER_OCCURRENCES>
      <LIST_OCCURRENCES>
      <OCCURRENCE>
        <ID>occ36</ID>
        <MNP>0</MNP>
        <DOC>0</DOC>
        <SENTENCE>2</SENTENCE>
        <START_POSITION>32</START_POSITION>
        <END_POSITION>33</END_POSITION>
        </OCCURRENCE>
      </LIST_OCCURRENCES>
      <TERM_CONFIDENCE>0.5</TERM_CONFIDENCE>
      <TERM_WEIGHTS>
            <WEIGHT name="CValue">0</WEIGHT>
            <WEIGHT name="CValue1">0</WEIGHT>
            <WEIGHT name="CValuePlus">0</WEIGHT>
            <WEIGHT name="CValuePlus1">2</WEIGHT>
            <WEIGHT name="CValueStar">N/A</WEIGHT>
            <WEIGHT name="CValueStarH">0</WEIGHT>
            <WEIGHT name="CValueStarM">N/A</WEIGHT>
            <WEIGHT name="CValueStarR">N/A</WEIGHT>
            <WEIGHT name="CValueWCard">0</WEIGHT>
            <WEIGHT name="CValueWCardPlus">2</WEIGHT>
            <WEIGHT name="D">1</WEIGHT>
            <WEIGHT name="DDW">0</WEIGHT>
            <WEIGHT name="Freq">1</WEIGHT>
            <WEIGHT name="IM">N/A</WEIGHT>
            <WEIGHT name="LLR">N/A</WEIGHT>
            <WEIGHT name="NormFreq">0.5</WEIGHT>
            <WEIGHT name="iLong">1</WEIGHT>
            <WEIGHT name="iTer">1</WEIGHT>
            <WEIGHT name="idf">0:0</WEIGHT>
            <WEIGHT name="ilnc">1</WEIGHT>
            <WEIGHT name="ilncFreq">1</WEIGHT>
            <WEIGHT name="nbdoc4tc">1</WEIGHT>
            <WEIGHT name="tf">0:1</WEIGHT>
            <WEIGHT name="tf-idf">0:0</WEIGHT>
      </TERM_WEIGHTS>
      <LOG_INFORMATION>YaTeA</LOG_INFORMATION>
    </TERM_CANDIDATE>
    <TERM_CANDIDATE MNP_STATUS="0">
      <ID>term26</ID>
      <FORM>2,5</FORM>
      <LEMMA>2,5</LEMMA>
      <MORPHOSYNTACTIC_FEATURES>
	    <SYNTACTIC_CATEGORY>NUM</SYNTACTIC_CATEGORY>
      </MORPHOSYNTACTIC_FEATURES>
      <HEAD>term26</HEAD>
      <NUMBER_OCCURRENCES>1</NUMBER_OCCURRENCES>
      <LIST_OCCURRENCES>
      <OCCURRENCE>
        <ID>occ42</ID>
        <MNP>0</MNP>
        <DOC>0</DOC>
        <SENTENCE>0</SENTENCE>
        <START_POSITION>93</START_POSITION>
        <END_POSITION>96</END_POSITION>
        </OCCURRENCE>
      </LIST_OCCURRENCES>
      <TERM_CONFIDENCE>0.5</TERM_CONFIDENCE>
      <TERM_WEIGHTS>
            <WEIGHT name="CValue">0</WEIGHT>
            <WEIGHT name="CValue1">0</WEIGHT>
            <WEIGHT name="CValuePlus">0</WEIGHT>
            <WEIGHT name="CValuePlus1">2</WEIGHT>
            <WEIGHT name="CValueStar">N/A</WEIGHT>
            <WEIGHT name="CValueStarH">N/A</WEIGHT>
            <WEIGHT name="CValueStarM">0</WEIGHT>
            <WEIGHT name="CValueStarR">N/A</WEIGHT>
            <WEIGHT name="CValueWCard">0</WEIGHT>
            <WEIGHT name="CValueWCardPlus">2</WEIGHT>
            <WEIGHT name="D">1</WEIGHT>
            <WEIGHT name="DDW">0</WEIGHT>
            <WEIGHT name="Freq">1</WEIGHT>
            <WEIGHT name="IM">N/A</WEIGHT>
            <WEIGHT name="LLR">N/A</WEIGHT>
            <WEIGHT name="NormFreq">0.5</WEIGHT>
            <WEIGHT name="iLong">1</WEIGHT>
            <WEIGHT name="iTer">0.5</WEIGHT>
            <WEIGHT name="idf">0:0</WEIGHT>
            <WEIGHT name="ilnc">0</WEIGHT>
            <WEIGHT name="ilncFreq">0</WEIGHT>
            <WEIGHT name="nbdoc4tc">1</WEIGHT>
            <WEIGHT name="tf">0:1</WEIGHT>
            <WEIGHT name="tf-idf">0:0</WEIGHT>
      </TERM_WEIGHTS>
      <LOG_INFORMATION>YaTeA</LOG_INFORMATION>
    </TERM_CANDIDATE>
    <TERM_CANDIDATE MNP_STATUS="1">
      <ID>term9</ID>
      <FORM>partie moteur</FORM>
      <LEMMA>partie moteur</LEMMA>
      <MORPHOSYNTACTIC_FEATURES>
	    <SYNTACTIC_CATEGORY>NOM ADJ</SYNTACTIC_CATEGORY>
      </MORPHOSYNTACTIC_FEATURES>
      <HEAD>term10</HEAD>
      <NUMBER_OCCURRENCES>1</NUMBER_OCCURRENCES>
      <LIST_OCCURRENCES>
      <OCCURRENCE>
        <ID>occ2</ID>
        <MNP>1</MNP>
        <DOC>0</DOC>
        <SENTENCE>0</SENTENCE>
        <START_POSITION>60</START_POSITION>
        <END_POSITION>73</END_POSITION>
        </OCCURRENCE>
      </LIST_OCCURRENCES>
      <TERM_CONFIDENCE>0.5</TERM_CONFIDENCE>
      <TERM_WEIGHTS>
            <WEIGHT name="CValue">1</WEIGHT>
            <WEIGHT name="CValue1">1.58496250072116</WEIGHT>
            <WEIGHT name="CValuePlus">1</WEIGHT>
            <WEIGHT name="CValuePlus1">1.58496250072116</WEIGHT>
            <WEIGHT name="CValueStar">N/A</WEIGHT>
            <WEIGHT name="CValueStarH">N/A</WEIGHT>
            <WEIGHT name="CValueStarM">N/A</WEIGHT>
            <WEIGHT name="CValueStarR">0.584962500721156</WEIGHT>
            <WEIGHT name="CValueWCard">0</WEIGHT>
            <WEIGHT name="CValueWCardPlus">0</WEIGHT>
            <WEIGHT name="D">1</WEIGHT>
            <WEIGHT name="DDW">0</WEIGHT>
            <WEIGHT name="Freq">1</WEIGHT>
            <WEIGHT name="IM">2</WEIGHT>
            <WEIGHT name="LLR">0.000115129154648748</WEIGHT>
            <WEIGHT name="NormFreq">0.5</WEIGHT>
            <WEIGHT name="iLong">0.5</WEIGHT>
            <WEIGHT name="iTer">0.333333333333333</WEIGHT>
            <WEIGHT name="idf">0:0</WEIGHT>
            <WEIGHT name="ilnc">0</WEIGHT>
            <WEIGHT name="ilncFreq">0</WEIGHT>
            <WEIGHT name="nbdoc4tc">1</WEIGHT>
            <WEIGHT name="tf">0:1</WEIGHT>
            <WEIGHT name="tf-idf">0:0</WEIGHT>
      </TERM_WEIGHTS>
      <LOG_INFORMATION>YaTeA</LOG_INFORMATION>
      <SYNTACTIC_ANALYSIS>
        <HEAD>
        term10
        </HEAD>
        <MODIFIER POSITION="AFTER">
        term11
        </MODIFIER>
      </SYNTACTIC_ANALYSIS>
    </TERM_CANDIDATE>
    <TERM_CANDIDATE MNP_STATUS="0">
      <ID>term27</ID>
      <FORM>MW</FORM>
      <LEMMA>MW</LEMMA>
      <MORPHOSYNTACTIC_FEATURES>
	    <SYNTACTIC_CATEGORY>NOM</SYNTACTIC_CATEGORY>
      </MORPHOSYNTACTIC_FEATURES>
      <HEAD>term27</HEAD>
      <NUMBER_OCCURRENCES>1</NUMBER_OCCURRENCES>
      <LIST_OCCURRENCES>
      <OCCURRENCE>
        <ID>occ43</ID>
        <MNP>0</MNP>
        <DOC>0</DOC>
        <SENTENCE>0</SENTENCE>
        <START_POSITION>97</START_POSITION>
        <END_POSITION>99</END_POSITION>
        </OCCURRENCE>
      </LIST_OCCURRENCES>
      <TERM_CONFIDENCE>0.5</TERM_CONFIDENCE>
      <TERM_WEIGHTS>
            <WEIGHT name="CValue">0</WEIGHT>
            <WEIGHT name="CValue1">0</WEIGHT>
            <WEIGHT name="CValuePlus">0</WEIGHT>
            <WEIGHT name="CValuePlus1">2</WEIGHT>
            <WEIGHT name="CValueStar">N/A</WEIGHT>
            <WEIGHT name="CValueStarH">0</WEIGHT>
            <WEIGHT name="CValueStarM">N/A</WEIGHT>
            <WEIGHT name="CValueStarR">N/A</WEIGHT>
            <WEIGHT name="CValueWCard">0</WEIGHT>
            <WEIGHT name="CValueWCardPlus">2</WEIGHT>
            <WEIGHT name="D">1</WEIGHT>
            <WEIGHT name="DDW">0</WEIGHT>
            <WEIGHT name="Freq">1</WEIGHT>
            <WEIGHT name="IM">N/A</WEIGHT>
            <WEIGHT name="LLR">N/A</WEIGHT>
            <WEIGHT name="NormFreq">0.5</WEIGHT>
            <WEIGHT name="iLong">1</WEIGHT>
            <WEIGHT name="iTer">1</WEIGHT>
            <WEIGHT name="idf">0:0</WEIGHT>
            <WEIGHT name="ilnc">1</WEIGHT>
            <WEIGHT name="ilncFreq">1</WEIGHT>
            <WEIGHT name="nbdoc4tc">1</WEIGHT>
            <WEIGHT name="tf">0:1</WEIGHT>
            <WEIGHT name="tf-idf">0:0</WEIGHT>
      </TERM_WEIGHTS>
      <LOG_INFORMATION>YaTeA</LOG_INFORMATION>
    </TERM_CANDIDATE>
    <TERM_CANDIDATE MNP_STATUS="0">
      <ID>term41</ID>
      <FORM>aviation civile</FORM>
      <LEMMA>aviation civil</LEMMA>
      <MORPHOSYNTACTIC_FEATURES>
	    <SYNTACTIC_CATEGORY>NOM ADJ</SYNTACTIC_CATEGORY>
      </MORPHOSYNTACTIC_FEATURES>
      <HEAD>term42</HEAD>
      <NUMBER_OCCURRENCES>1</NUMBER_OCCURRENCES>
      <LIST_OCCURRENCES>
      <OCCURRENCE>
        <ID>occ54</ID>
        <MNP>0</MNP>
        <DOC>0</DOC>
        <SENTENCE>4</SENTENCE>
        <START_POSITION>79</START_POSITION>
        <END_POSITION>94</END_POSITION>
        </OCCURRENCE>
      </LIST_OCCURRENCES>
      <TERM_CONFIDENCE>0.5</TERM_CONFIDENCE>
      <TERM_WEIGHTS>
            <WEIGHT name="CValue">0</WEIGHT>
            <WEIGHT name="CValue1">0</WEIGHT>
            <WEIGHT name="CValuePlus">2</WEIGHT>
            <WEIGHT name="CValuePlus1">3.16992500144231</WEIGHT>
            <WEIGHT name="CValueStar">N/A</WEIGHT>
            <WEIGHT name="CValueStarH">N/A</WEIGHT>
            <WEIGHT name="CValueStarM">0</WEIGHT>
            <WEIGHT name="CValueStarR">N/A</WEIGHT>
            <WEIGHT name="CValueWCard">0</WEIGHT>
            <WEIGHT name="CValueWCardPlus">2</WEIGHT>
            <WEIGHT name="D">1</WEIGHT>
            <WEIGHT name="DDW">0</WEIGHT>
            <WEIGHT name="Freq">1</WEIGHT>
            <WEIGHT name="IM">2</WEIGHT>
            <WEIGHT name="LLR">0.000115129154648748</WEIGHT>
            <WEIGHT name="NormFreq">0.5</WEIGHT>
            <WEIGHT name="iLong">0.5</WEIGHT>
            <WEIGHT name="iTer">0.333333333333333</WEIGHT>
            <WEIGHT name="idf">0:0</WEIGHT>
            <WEIGHT name="ilnc">0</WEIGHT>
            <WEIGHT name="ilncFreq">0</WEIGHT>
            <WEIGHT name="nbdoc4tc">1</WEIGHT>
            <WEIGHT name="tf">0:1</WEIGHT>
            <WEIGHT name="tf-idf">0:0</WEIGHT>
      </TERM_WEIGHTS>
      <LOG_INFORMATION>YaTeA</LOG_INFORMATION>
      <SYNTACTIC_ANALYSIS>
        <HEAD>
        term42
        </HEAD>
        <MODIFIER POSITION="AFTER">
        term43
        </MODIFIER>
      </SYNTACTIC_ANALYSIS>
    </TERM_CANDIDATE>
    <TERM_CANDIDATE MNP_STATUS="1">
      <ID>term35</ID>
      <FORM>opération</FORM>
      <LEMMA>opération</LEMMA>
      <MORPHOSYNTACTIC_FEATURES>
	    <SYNTACTIC_CATEGORY>NOM</SYNTACTIC_CATEGORY>
      </MORPHOSYNTACTIC_FEATURES>
      <HEAD>term35</HEAD>
      <NUMBER_OCCURRENCES>1</NUMBER_OCCURRENCES>
      <LIST_OCCURRENCES>
      <OCCURRENCE>
        <ID>occ50</ID>
        <MNP>1</MNP>
        <DOC>0</DOC>
        <SENTENCE>6</SENTENCE>
        <START_POSITION>6</START_POSITION>
        <END_POSITION>15</END_POSITION>
        </OCCURRENCE>
      </LIST_OCCURRENCES>
      <TERM_CONFIDENCE>0.5</TERM_CONFIDENCE>
      <TERM_WEIGHTS>
            <WEIGHT name="CValue">0</WEIGHT>
            <WEIGHT name="CValue1">1</WEIGHT>
            <WEIGHT name="CValuePlus">0</WEIGHT>
            <WEIGHT name="CValuePlus1">1</WEIGHT>
            <WEIGHT name="CValueStar">N/A</WEIGHT>
            <WEIGHT name="CValueStarH">N/A</WEIGHT>
            <WEIGHT name="CValueStarM">N/A</WEIGHT>
            <WEIGHT name="CValueStarR">1</WEIGHT>
            <WEIGHT name="CValueWCard">0</WEIGHT>
            <WEIGHT name="CValueWCardPlus">0</WEIGHT>
            <WEIGHT name="D">1</WEIGHT>
            <WEIGHT name="DDW">0</WEIGHT>
            <WEIGHT name="Freq">1</WEIGHT>
            <WEIGHT name="IM">N/A</WEIGHT>
            <WEIGHT name="LLR">N/A</WEIGHT>
            <WEIGHT name="NormFreq">0.5</WEIGHT>
            <WEIGHT name="iLong">1</WEIGHT>
            <WEIGHT name="iTer">0.5</WEIGHT>
            <WEIGHT name="idf">0:0</WEIGHT>
            <WEIGHT name="ilnc">0</WEIGHT>
            <WEIGHT name="ilncFreq">0</WEIGHT>
            <WEIGHT name="nbdoc4tc">1</WEIGHT>
            <WEIGHT name="tf">0:1</WEIGHT>
            <WEIGHT name="tf-idf">0:0</WEIGHT>
      </TERM_WEIGHTS>
      <LOG_INFORMATION>YaTeA</LOG_INFORMATION>
    </TERM_CANDIDATE>
    <TERM_CANDIDATE MNP_STATUS="1">
      <ID>term12</ID>
      <FORM>périmètre de sécurité de 300 m</FORM>
      <LEMMA>périmètre de sécurité de 300 m</LEMMA>
      <MORPHOSYNTACTIC_FEATURES>
	    <SYNTACTIC_CATEGORY>NOM de NOM de NUM NOM</SYNTACTIC_CATEGORY>
      </MORPHOSYNTACTIC_FEATURES>
      <HEAD>term14</HEAD>
      <NUMBER_OCCURRENCES>1</NUMBER_OCCURRENCES>
      <LIST_OCCURRENCES>
      <OCCURRENCE>
        <ID>occ5</ID>
        <MNP>1</MNP>
        <DOC>0</DOC>
        <SENTENCE>2</SENTENCE>
        <START_POSITION>3</START_POSITION>
        <END_POSITION>33</END_POSITION>
        </OCCURRENCE>
      </LIST_OCCURRENCES>
      <TERM_CONFIDENCE>0.5</TERM_CONFIDENCE>
      <TERM_WEIGHTS>
            <WEIGHT name="CValue">2.58496250072116</WEIGHT>
            <WEIGHT name="CValue1">2.8073549220576</WEIGHT>
            <WEIGHT name="CValuePlus">2.58496250072116</WEIGHT>
            <WEIGHT name="CValuePlus1">2.8073549220576</WEIGHT>
            <WEIGHT name="CValueStar">N/A</WEIGHT>
            <WEIGHT name="CValueStarH">N/A</WEIGHT>
            <WEIGHT name="CValueStarM">N/A</WEIGHT>
            <WEIGHT name="CValueStarR">0.222392421336448</WEIGHT>
            <WEIGHT name="CValueWCard">0</WEIGHT>
            <WEIGHT name="CValueWCardPlus">0</WEIGHT>
            <WEIGHT name="D">1</WEIGHT>
            <WEIGHT name="DDW">0</WEIGHT>
            <WEIGHT name="Freq">1</WEIGHT>
            <WEIGHT name="IM">1</WEIGHT>
            <WEIGHT name="LLR">0.000115129154648748</WEIGHT>
            <WEIGHT name="NormFreq">0.5</WEIGHT>
            <WEIGHT name="iLong">0.166666666666667</WEIGHT>
            <WEIGHT name="iTer">0.142857142857143</WEIGHT>
            <WEIGHT name="idf">0:0</WEIGHT>
            <WEIGHT name="ilnc">0</WEIGHT>
            <WEIGHT name="ilncFreq">0</WEIGHT>
            <WEIGHT name="nbdoc4tc">1</WEIGHT>
            <WEIGHT name="tf">0:1</WEIGHT>
            <WEIGHT name="tf-idf">0:0</WEIGHT>
      </TERM_WEIGHTS>
      <LIST_RELIABLE_ANCHORS>
        <RELIABLE_ANCHOR>
          <ID>term13</ID>
          <FORM>périmètre de sécurité</FORM>
          <ORIGIN>endogenous</ORIGIN>
        </RELIABLE_ANCHOR>
      </LIST_RELIABLE_ANCHORS>
      <LOG_INFORMATION>YaTeA</LOG_INFORMATION>
      <SYNTACTIC_ANALYSIS>
        <HEAD>
        term13
        </HEAD>
        <MODIFIER POSITION="AFTER">
        term16
        </MODIFIER>
        <PREP>
        de
        </PREP>
      </SYNTACTIC_ANALYSIS>
    </TERM_CANDIDATE>
    <TERM_CANDIDATE MNP_STATUS="0">
      <ID>term37</ID>
      <FORM>basculement</FORM>
      <LEMMA>basculement</LEMMA>
      <MORPHOSYNTACTIC_FEATURES>
	    <SYNTACTIC_CATEGORY>NOM</SYNTACTIC_CATEGORY>
      </MORPHOSYNTACTIC_FEATURES>
      <HEAD>term37</HEAD>
      <NUMBER_OCCURRENCES>1</NUMBER_OCCURRENCES>
      <LIST_OCCURRENCES>
      <OCCURRENCE>
        <ID>occ51</ID>
        <MNP>0</MNP>
        <DOC>0</DOC>
        <SENTENCE>5</SENTENCE>
        <START_POSITION>121</START_POSITION>
        <END_POSITION>132</END_POSITION>
        </OCCURRENCE>
      </LIST_OCCURRENCES>
      <TERM_CONFIDENCE>0.5</TERM_CONFIDENCE>
      <TERM_WEIGHTS>
            <WEIGHT name="CValue">0</WEIGHT>
            <WEIGHT name="CValue1">0</WEIGHT>
            <WEIGHT name="CValuePlus">0</WEIGHT>
            <WEIGHT name="CValuePlus1">2</WEIGHT>
            <WEIGHT name="CValueStar">N/A</WEIGHT>
            <WEIGHT name="CValueStarH">0</WEIGHT>
            <WEIGHT name="CValueStarM">N/A</WEIGHT>
            <WEIGHT name="CValueStarR">N/A</WEIGHT>
            <WEIGHT name="CValueWCard">0</WEIGHT>
            <WEIGHT name="CValueWCardPlus">2</WEIGHT>
            <WEIGHT name="D">1</WEIGHT>
            <WEIGHT name="DDW">0</WEIGHT>
            <WEIGHT name="Freq">1</WEIGHT>
            <WEIGHT name="IM">N/A</WEIGHT>
            <WEIGHT name="LLR">N/A</WEIGHT>
            <WEIGHT name="NormFreq">0.5</WEIGHT>
            <WEIGHT name="iLong">1</WEIGHT>
            <WEIGHT name="iTer">1</WEIGHT>
            <WEIGHT name="idf">0:0</WEIGHT>
            <WEIGHT name="ilnc">1</WEIGHT>
            <WEIGHT name="ilncFreq">1</WEIGHT>
            <WEIGHT name="nbdoc4tc">1</WEIGHT>
            <WEIGHT name="tf">0:1</WEIGHT>
            <WEIGHT name="tf-idf">0:0</WEIGHT>
      </TERM_WEIGHTS>
      <LOG_INFORMATION>YaTeA</LOG_INFORMATION>
    </TERM_CANDIDATE>
    <TERM_CANDIDATE MNP_STATUS="0">
      <ID>term32</ID>
      <FORM>incident</FORM>
      <LEMMA>incident</LEMMA>
      <MORPHOSYNTACTIC_FEATURES>
	    <SYNTACTIC_CATEGORY>NOM</SYNTACTIC_CATEGORY>
      </MORPHOSYNTACTIC_FEATURES>
      <HEAD>term32</HEAD>
      <NUMBER_OCCURRENCES>1</NUMBER_OCCURRENCES>
      <LIST_OCCURRENCES>
      <OCCURRENCE>
        <ID>occ47</ID>
        <MNP>0</MNP>
        <DOC>0</DOC>
        <SENTENCE>5</SENTENCE>
        <START_POSITION>20</START_POSITION>
        <END_POSITION>28</END_POSITION>
        </OCCURRENCE>
      </LIST_OCCURRENCES>
      <TERM_CONFIDENCE>0.5</TERM_CONFIDENCE>
      <TERM_WEIGHTS>
            <WEIGHT name="CValue">0</WEIGHT>
            <WEIGHT name="CValue1">0</WEIGHT>
            <WEIGHT name="CValuePlus">0</WEIGHT>
            <WEIGHT name="CValuePlus1">2</WEIGHT>
            <WEIGHT name="CValueStar">N/A</WEIGHT>
            <WEIGHT name="CValueStarH">0</WEIGHT>
            <WEIGHT name="CValueStarM">N/A</WEIGHT>
            <WEIGHT name="CValueStarR">N/A</WEIGHT>
            <WEIGHT name="CValueWCard">0</WEIGHT>
            <WEIGHT name="CValueWCardPlus">2</WEIGHT>
            <WEIGHT name="D">1</WEIGHT>
            <WEIGHT name="DDW">0</WEIGHT>
            <WEIGHT name="Freq">1</WEIGHT>
            <WEIGHT name="IM">N/A</WEIGHT>
            <WEIGHT name="LLR">N/A</WEIGHT>
            <WEIGHT name="NormFreq">0.5</WEIGHT>
            <WEIGHT name="iLong">1</WEIGHT>
            <WEIGHT name="iTer">1</WEIGHT>
            <WEIGHT name="idf">0:0</WEIGHT>
            <WEIGHT name="ilnc">1</WEIGHT>
            <WEIGHT name="ilncFreq">1</WEIGHT>
            <WEIGHT name="nbdoc4tc">1</WEIGHT>
            <WEIGHT name="tf">0:1</WEIGHT>
            <WEIGHT name="tf-idf">0:0</WEIGHT>
      </TERM_WEIGHTS>
      <LOG_INFORMATION>YaTeA</LOG_INFORMATION>
    </TERM_CANDIDATE>
    <TERM_CANDIDATE MNP_STATUS="0">
      <ID>term42</ID>
      <FORM>aviation</FORM>
      <LEMMA>aviation</LEMMA>
      <MORPHOSYNTACTIC_FEATURES>
	    <SYNTACTIC_CATEGORY>NOM</SYNTACTIC_CATEGORY>
      </MORPHOSYNTACTIC_FEATURES>
      <HEAD>term42</HEAD>
      <NUMBER_OCCURRENCES>1</NUMBER_OCCURRENCES>
      <LIST_OCCURRENCES>
      <OCCURRENCE>
        <ID>occ55</ID>
        <MNP>0</MNP>
        <DOC>0</DOC>
        <SENTENCE>4</SENTENCE>
        <START_POSITION>79</START_POSITION>
        <END_POSITION>87</END_POSITION>
        </OCCURRENCE>
      </LIST_OCCURRENCES>
      <TERM_CONFIDENCE>0.5</TERM_CONFIDENCE>
      <TERM_WEIGHTS>
            <WEIGHT name="CValue">0</WEIGHT>
            <WEIGHT name="CValue1">0</WEIGHT>
            <WEIGHT name="CValuePlus">0</WEIGHT>
            <WEIGHT name="CValuePlus1">2</WEIGHT>
            <WEIGHT name="CValueStar">N/A</WEIGHT>
            <WEIGHT name="CValueStarH">0</WEIGHT>
            <WEIGHT name="CValueStarM">N/A</WEIGHT>
            <WEIGHT name="CValueStarR">N/A</WEIGHT>
            <WEIGHT name="CValueWCard">0</WEIGHT>
            <WEIGHT name="CValueWCardPlus">2</WEIGHT>
            <WEIGHT name="D">1</WEIGHT>
            <WEIGHT name="DDW">0</WEIGHT>
            <WEIGHT name="Freq">1</WEIGHT>
            <WEIGHT name="IM">N/A</WEIGHT>
            <WEIGHT name="LLR">N/A</WEIGHT>
            <WEIGHT name="NormFreq">0.5</WEIGHT>
            <WEIGHT name="iLong">1</WEIGHT>
            <WEIGHT name="iTer">1</WEIGHT>
            <WEIGHT name="idf">0:0</WEIGHT>
            <WEIGHT name="ilnc">1</WEIGHT>
            <WEIGHT name="ilncFreq">1</WEIGHT>
            <WEIGHT name="nbdoc4tc">1</WEIGHT>
            <WEIGHT name="tf">0:1</WEIGHT>
            <WEIGHT name="tf-idf">0:0</WEIGHT>
      </TERM_WEIGHTS>
      <LOG_INFORMATION>YaTeA</LOG_INFORMATION>
    </TERM_CANDIDATE>
    <TERM_CANDIDATE MNP_STATUS="1">
      <ID>term36</ID>
      <FORM>basculement à l&apos; explosif</FORM>
      <LEMMA>basculement à le explosif</LEMMA>
      <MORPHOSYNTACTIC_FEATURES>
	    <SYNTACTIC_CATEGORY>NOM à DET:ART NOM</SYNTACTIC_CATEGORY>
      </MORPHOSYNTACTIC_FEATURES>
      <HEAD>term37</HEAD>
      <NUMBER_OCCURRENCES>1</NUMBER_OCCURRENCES>
      <LIST_OCCURRENCES>
      <OCCURRENCE>
        <ID>occ16</ID>
        <MNP>1</MNP>
        <DOC>0</DOC>
        <SENTENCE>5</SENTENCE>
        <START_POSITION>121</START_POSITION>
        <END_POSITION>146</END_POSITION>
        </OCCURRENCE>
      </LIST_OCCURRENCES>
      <TERM_CONFIDENCE>0.5</TERM_CONFIDENCE>
      <TERM_WEIGHTS>
            <WEIGHT name="CValue">2</WEIGHT>
            <WEIGHT name="CValue1">2.32192809488736</WEIGHT>
            <WEIGHT name="CValuePlus">2</WEIGHT>
            <WEIGHT name="CValuePlus1">2.32192809488736</WEIGHT>
            <WEIGHT name="CValueStar">N/A</WEIGHT>
            <WEIGHT name="CValueStarH">N/A</WEIGHT>
            <WEIGHT name="CValueStarM">N/A</WEIGHT>
            <WEIGHT name="CValueStarR">0.321928094887362</WEIGHT>
            <WEIGHT name="CValueWCard">0</WEIGHT>
            <WEIGHT name="CValueWCardPlus">0</WEIGHT>
            <WEIGHT name="D">1</WEIGHT>
            <WEIGHT name="DDW">0</WEIGHT>
            <WEIGHT name="Freq">1</WEIGHT>
            <WEIGHT name="IM">2</WEIGHT>
            <WEIGHT name="LLR">0.000115129154648748</WEIGHT>
            <WEIGHT name="NormFreq">0.5</WEIGHT>
            <WEIGHT name="iLong">0.25</WEIGHT>
            <WEIGHT name="iTer">0.2</WEIGHT>
            <WEIGHT name="idf">0:0</WEIGHT>
            <WEIGHT name="ilnc">0</WEIGHT>
            <WEIGHT name="ilncFreq">0</WEIGHT>
            <WEIGHT name="nbdoc4tc">1</WEIGHT>
            <WEIGHT name="tf">0:1</WEIGHT>
            <WEIGHT name="tf-idf">0:0</WEIGHT>
      </TERM_WEIGHTS>
      <LOG_INFORMATION>YaTeA</LOG_INFORMATION>
      <SYNTACTIC_ANALYSIS>
        <HEAD>
        term37
        </HEAD>
        <MODIFIER POSITION="AFTER">
        term38
        </MODIFIER>
        <PREP>
        à
        </PREP>
        <DETERMINER>
        l'
        </DETERMINER>
      </SYNTACTIC_ANALYSIS>
    </TERM_CANDIDATE>
    <TERM_CANDIDATE MNP_STATUS="0">
      <ID>term5</ID>
      <FORM>sinistrée</FORM>
      <LEMMA>sinistré</LEMMA>
      <MORPHOSYNTACTIC_FEATURES>
	    <SYNTACTIC_CATEGORY>ADJ</SYNTACTIC_CATEGORY>
      </MORPHOSYNTACTIC_FEATURES>
      <HEAD>term5</HEAD>
      <NUMBER_OCCURRENCES>1</NUMBER_OCCURRENCES>
      <LIST_OCCURRENCES>
      <OCCURRENCE>
        <ID>occ26</ID>
        <MNP>0</MNP>
        <DOC>0</DOC>
        <SENTENCE>5</SENTENCE>
        <START_POSITION>83</START_POSITION>
        <END_POSITION>92</END_POSITION>
        </OCCURRENCE>
      </LIST_OCCURRENCES>
      <TERM_CONFIDENCE>0.5</TERM_CONFIDENCE>
      <TERM_WEIGHTS>
            <WEIGHT name="CValue">0</WEIGHT>
            <WEIGHT name="CValue1">0</WEIGHT>
            <WEIGHT name="CValuePlus">0</WEIGHT>
            <WEIGHT name="CValuePlus1">2</WEIGHT>
            <WEIGHT name="CValueStar">N/A</WEIGHT>
            <WEIGHT name="CValueStarH">N/A</WEIGHT>
            <WEIGHT name="CValueStarM">0</WEIGHT>
            <WEIGHT name="CValueStarR">N/A</WEIGHT>
            <WEIGHT name="CValueWCard">0</WEIGHT>
            <WEIGHT name="CValueWCardPlus">2</WEIGHT>
            <WEIGHT name="D">1</WEIGHT>
            <WEIGHT name="DDW">0</WEIGHT>
            <WEIGHT name="Freq">1</WEIGHT>
            <WEIGHT name="IM">N/A</WEIGHT>
            <WEIGHT name="LLR">N/A</WEIGHT>
            <WEIGHT name="NormFreq">0.5</WEIGHT>
            <WEIGHT name="iLong">1</WEIGHT>
            <WEIGHT name="iTer">0.5</WEIGHT>
            <WEIGHT name="idf">0:0</WEIGHT>
            <WEIGHT name="ilnc">0</WEIGHT>
            <WEIGHT name="ilncFreq">0</WEIGHT>
            <WEIGHT name="nbdoc4tc">1</WEIGHT>
            <WEIGHT name="tf">0:1</WEIGHT>
            <WEIGHT name="tf-idf">0:0</WEIGHT>
      </TERM_WEIGHTS>
      <LOG_INFORMATION>YaTeA</LOG_INFORMATION>
    </TERM_CANDIDATE>
    <TERM_CANDIDATE MNP_STATUS="1">
      <ID>term22</ID>
      <FORM>presse</FORM>
      <LEMMA>presse</LEMMA>
      <MORPHOSYNTACTIC_FEATURES>
	    <SYNTACTIC_CATEGORY>NOM</SYNTACTIC_CATEGORY>
      </MORPHOSYNTACTIC_FEATURES>
      <HEAD>term22</HEAD>
      <NUMBER_OCCURRENCES>1</NUMBER_OCCURRENCES>
      <LIST_OCCURRENCES>
      <OCCURRENCE>
        <ID>occ39</ID>
        <MNP>1</MNP>
        <DOC>0</DOC>
        <SENTENCE>5</SENTENCE>
        <START_POSITION>3</START_POSITION>
        <END_POSITION>9</END_POSITION>
        </OCCURRENCE>
      </LIST_OCCURRENCES>
      <TERM_CONFIDENCE>0.5</TERM_CONFIDENCE>
      <TERM_WEIGHTS>
            <WEIGHT name="CValue">0</WEIGHT>
            <WEIGHT name="CValue1">1</WEIGHT>
            <WEIGHT name="CValuePlus">0</WEIGHT>
            <WEIGHT name="CValuePlus1">1</WEIGHT>
            <WEIGHT name="CValueStar">N/A</WEIGHT>
            <WEIGHT name="CValueStarH">N/A</WEIGHT>
            <WEIGHT name="CValueStarM">N/A</WEIGHT>
            <WEIGHT name="CValueStarR">1</WEIGHT>
            <WEIGHT name="CValueWCard">0</WEIGHT>
            <WEIGHT name="CValueWCardPlus">0</WEIGHT>
            <WEIGHT name="D">1</WEIGHT>
            <WEIGHT name="DDW">0</WEIGHT>
            <WEIGHT name="Freq">1</WEIGHT>
            <WEIGHT name="IM">N/A</WEIGHT>
            <WEIGHT name="LLR">N/A</WEIGHT>
            <WEIGHT name="NormFreq">0.5</WEIGHT>
            <WEIGHT name="iLong">1</WEIGHT>
            <WEIGHT name="iTer">0.5</WEIGHT>
            <WEIGHT name="idf">0:0</WEIGHT>
            <WEIGHT name="ilnc">0</WEIGHT>
            <WEIGHT name="ilncFreq">0</WEIGHT>
            <WEIGHT name="nbdoc4tc">1</WEIGHT>
            <WEIGHT name="tf">0:1</WEIGHT>
            <WEIGHT name="tf-idf">0:0</WEIGHT>
      </TERM_WEIGHTS>
      <LOG_INFORMATION>YaTeA</LOG_INFORMATION>
    </TERM_CANDIDATE>
    <TERM_CANDIDATE MNP_STATUS="0">
      <ID>term21</ID>
      <FORM>éolien</FORM>
      <LEMMA>éolien</LEMMA>
      <MORPHOSYNTACTIC_FEATURES>
	    <SYNTACTIC_CATEGORY>ADJ</SYNTACTIC_CATEGORY>
      </MORPHOSYNTACTIC_FEATURES>
      <HEAD>term21</HEAD>
      <NUMBER_OCCURRENCES>1</NUMBER_OCCURRENCES>
      <LIST_OCCURRENCES>
      <OCCURRENCE>
        <ID>occ38</ID>
        <MNP>0</MNP>
        <DOC>0</DOC>
        <SENTENCE>1</SENTENCE>
        <START_POSITION>8</START_POSITION>
        <END_POSITION>14</END_POSITION>
        </OCCURRENCE>
      </LIST_OCCURRENCES>
      <TERM_CONFIDENCE>0.5</TERM_CONFIDENCE>
      <TERM_WEIGHTS>
            <WEIGHT name="CValue">0</WEIGHT>
            <WEIGHT name="CValue1">0</WEIGHT>
            <WEIGHT name="CValuePlus">0</WEIGHT>
            <WEIGHT name="CValuePlus1">2</WEIGHT>
            <WEIGHT name="CValueStar">N/A</WEIGHT>
            <WEIGHT name="CValueStarH">N/A</WEIGHT>
            <WEIGHT name="CValueStarM">0</WEIGHT>
            <WEIGHT name="CValueStarR">N/A</WEIGHT>
            <WEIGHT name="CValueWCard">0</WEIGHT>
            <WEIGHT name="CValueWCardPlus">2</WEIGHT>
            <WEIGHT name="D">1</WEIGHT>
            <WEIGHT name="DDW">0</WEIGHT>
            <WEIGHT name="Freq">1</WEIGHT>
            <WEIGHT name="IM">N/A</WEIGHT>
            <WEIGHT name="LLR">N/A</WEIGHT>
            <WEIGHT name="NormFreq">0.5</WEIGHT>
            <WEIGHT name="iLong">1</WEIGHT>
            <WEIGHT name="iTer">0.5</WEIGHT>
            <WEIGHT name="idf">0:0</WEIGHT>
            <WEIGHT name="ilnc">0</WEIGHT>
            <WEIGHT name="ilncFreq">0</WEIGHT>
            <WEIGHT name="nbdoc4tc">1</WEIGHT>
            <WEIGHT name="tf">0:1</WEIGHT>
            <WEIGHT name="tf-idf">0:0</WEIGHT>
      </TERM_WEIGHTS>
      <LOG_INFORMATION>YaTeA</LOG_INFORMATION>
    </TERM_CANDIDATE>
    <TERM_CANDIDATE MNP_STATUS="1">
      <ID>term30</ID>
      <FORM>feu</FORM>
      <LEMMA>feu</LEMMA>
      <MORPHOSYNTACTIC_FEATURES>
	    <SYNTACTIC_CATEGORY>NOM</SYNTACTIC_CATEGORY>
      </MORPHOSYNTACTIC_FEATURES>
      <HEAD>term30</HEAD>
      <NUMBER_OCCURRENCES>1</NUMBER_OCCURRENCES>
      <LIST_OCCURRENCES>
      <OCCURRENCE>
        <ID>occ46</ID>
        <MNP>1</MNP>
        <DOC>0</DOC>
        <SENTENCE>3</SENTENCE>
        <START_POSITION>3</START_POSITION>
        <END_POSITION>6</END_POSITION>
        </OCCURRENCE>
      </LIST_OCCURRENCES>
      <TERM_CONFIDENCE>0.5</TERM_CONFIDENCE>
      <TERM_WEIGHTS>
            <WEIGHT name="CValue">0</WEIGHT>
            <WEIGHT name="CValue1">2</WEIGHT>
            <WEIGHT name="CValuePlus">0</WEIGHT>
            <WEIGHT name="CValuePlus1">2</WEIGHT>
            <WEIGHT name="CValueStar">N/A</WEIGHT>
            <WEIGHT name="CValueStarH">N/A</WEIGHT>
            <WEIGHT name="CValueStarM">N/A</WEIGHT>
            <WEIGHT name="CValueStarR">2</WEIGHT>
            <WEIGHT name="CValueWCard">0</WEIGHT>
            <WEIGHT name="CValueWCardPlus">0</WEIGHT>
            <WEIGHT name="D">1</WEIGHT>
            <WEIGHT name="DDW">0</WEIGHT>
            <WEIGHT name="Freq">1</WEIGHT>
            <WEIGHT name="IM">N/A</WEIGHT>
            <WEIGHT name="LLR">N/A</WEIGHT>
            <WEIGHT name="NormFreq">0.5</WEIGHT>
            <WEIGHT name="iLong">1</WEIGHT>
            <WEIGHT name="iTer">0.5</WEIGHT>
            <WEIGHT name="idf">0:0</WEIGHT>
            <WEIGHT name="ilnc">0</WEIGHT>
            <WEIGHT name="ilncFreq">0</WEIGHT>
            <WEIGHT name="nbdoc4tc">1</WEIGHT>
            <WEIGHT name="tf">0:1</WEIGHT>
            <WEIGHT name="tf-idf">0:0</WEIGHT>
      </TERM_WEIGHTS>
      <LOG_INFORMATION>YaTeA</LOG_INFORMATION>
    </TERM_CANDIDATE>
    <TERM_CANDIDATE MNP_STATUS="1">
      <ID>term0</ID>
      <FORM>place</FORM>
      <LEMMA>place</LEMMA>
      <MORPHOSYNTACTIC_FEATURES>
	    <SYNTACTIC_CATEGORY>NOM</SYNTACTIC_CATEGORY>
      </MORPHOSYNTACTIC_FEATURES>
      <HEAD>term0</HEAD>
      <NUMBER_OCCURRENCES>2</NUMBER_OCCURRENCES>
      <LIST_OCCURRENCES>
      <OCCURRENCE>
        <ID>occ21</ID>
        <MNP>1</MNP>
        <DOC>0</DOC>
        <SENTENCE>2</SENTENCE>
        <START_POSITION>45</START_POSITION>
        <END_POSITION>50</END_POSITION>
        </OCCURRENCE>
      <OCCURRENCE>
        <ID>occ22</ID>
        <MNP>1</MNP>
        <DOC>0</DOC>
        <SENTENCE>6</SENTENCE>
        <START_POSITION>37</START_POSITION>
        <END_POSITION>42</END_POSITION>
        </OCCURRENCE>
      </LIST_OCCURRENCES>
      <TERM_CONFIDENCE>0.5</TERM_CONFIDENCE>
      <TERM_WEIGHTS>
            <WEIGHT name="CValue">0</WEIGHT>
            <WEIGHT name="CValue1">2</WEIGHT>
            <WEIGHT name="CValuePlus">0</WEIGHT>
            <WEIGHT name="CValuePlus1">2</WEIGHT>
            <WEIGHT name="CValueStar">N/A</WEIGHT>
            <WEIGHT name="CValueStarH">N/A</WEIGHT>
            <WEIGHT name="CValueStarM">N/A</WEIGHT>
            <WEIGHT name="CValueStarR">2</WEIGHT>
            <WEIGHT name="CValueWCard">0</WEIGHT>
            <WEIGHT name="CValueWCardPlus">0</WEIGHT>
            <WEIGHT name="D">1</WEIGHT>
            <WEIGHT name="DDW">0</WEIGHT>
            <WEIGHT name="Freq">2</WEIGHT>
            <WEIGHT name="IM">N/A</WEIGHT>
            <WEIGHT name="LLR">N/A</WEIGHT>
            <WEIGHT name="NormFreq">1</WEIGHT>
            <WEIGHT name="iLong">2</WEIGHT>
            <WEIGHT name="iTer">1</WEIGHT>
            <WEIGHT name="idf">0:0</WEIGHT>
            <WEIGHT name="ilnc">0</WEIGHT>
            <WEIGHT name="ilncFreq">0</WEIGHT>
            <WEIGHT name="nbdoc4tc">1</WEIGHT>
            <WEIGHT name="tf">0:2</WEIGHT>
            <WEIGHT name="tf-idf">0:0</WEIGHT>
      </TERM_WEIGHTS>
      <LOG_INFORMATION>YaTeA</LOG_INFORMATION>
    </TERM_CANDIDATE>
    <TERM_CANDIDATE MNP_STATUS="0">
      <ID>term38</ID>
      <FORM>explosif</FORM>
      <LEMMA>explosif</LEMMA>
      <MORPHOSYNTACTIC_FEATURES>
	    <SYNTACTIC_CATEGORY>NOM</SYNTACTIC_CATEGORY>
      </MORPHOSYNTACTIC_FEATURES>
      <HEAD>term38</HEAD>
      <NUMBER_OCCURRENCES>1</NUMBER_OCCURRENCES>
      <LIST_OCCURRENCES>
      <OCCURRENCE>
        <ID>occ52</ID>
        <MNP>0</MNP>
        <DOC>0</DOC>
        <SENTENCE>5</SENTENCE>
        <START_POSITION>138</START_POSITION>
        <END_POSITION>146</END_POSITION>
        </OCCURRENCE>
      </LIST_OCCURRENCES>
      <TERM_CONFIDENCE>0.5</TERM_CONFIDENCE>
      <TERM_WEIGHTS>
            <WEIGHT name="CValue">0</WEIGHT>
            <WEIGHT name="CValue1">0</WEIGHT>
            <WEIGHT name="CValuePlus">0</WEIGHT>
            <WEIGHT name="CValuePlus1">2</WEIGHT>
            <WEIGHT name="CValueStar">N/A</WEIGHT>
            <WEIGHT name="CValueStarH">N/A</WEIGHT>
            <WEIGHT name="CValueStarM">0</WEIGHT>
            <WEIGHT name="CValueStarR">N/A</WEIGHT>
            <WEIGHT name="CValueWCard">0</WEIGHT>
            <WEIGHT name="CValueWCardPlus">2</WEIGHT>
            <WEIGHT name="D">1</WEIGHT>
            <WEIGHT name="DDW">0</WEIGHT>
            <WEIGHT name="Freq">1</WEIGHT>
            <WEIGHT name="IM">N/A</WEIGHT>
            <WEIGHT name="LLR">N/A</WEIGHT>
            <WEIGHT name="NormFreq">0.5</WEIGHT>
            <WEIGHT name="iLong">1</WEIGHT>
            <WEIGHT name="iTer">0.5</WEIGHT>
            <WEIGHT name="idf">0:0</WEIGHT>
            <WEIGHT name="ilnc">0</WEIGHT>
            <WEIGHT name="ilncFreq">0</WEIGHT>
            <WEIGHT name="nbdoc4tc">1</WEIGHT>
            <WEIGHT name="tf">0:1</WEIGHT>
            <WEIGHT name="tf-idf">0:0</WEIGHT>
      </TERM_WEIGHTS>
      <LOG_INFORMATION>YaTeA</LOG_INFORMATION>
    </TERM_CANDIDATE>
    <TERM_CANDIDATE MNP_STATUS="0">
      <ID>term25</ID>
      <FORM>2,5 MW</FORM>
      <LEMMA>2,5 MW</LEMMA>
      <MORPHOSYNTACTIC_FEATURES>
	    <SYNTACTIC_CATEGORY>NUM NOM</SYNTACTIC_CATEGORY>
      </MORPHOSYNTACTIC_FEATURES>
      <HEAD>term27</HEAD>
      <NUMBER_OCCURRENCES>1</NUMBER_OCCURRENCES>
      <LIST_OCCURRENCES>
      <OCCURRENCE>
        <ID>occ41</ID>
        <MNP>0</MNP>
        <DOC>0</DOC>
        <SENTENCE>0</SENTENCE>
        <START_POSITION>93</START_POSITION>
        <END_POSITION>99</END_POSITION>
        </OCCURRENCE>
      </LIST_OCCURRENCES>
      <TERM_CONFIDENCE>0.5</TERM_CONFIDENCE>
      <TERM_WEIGHTS>
            <WEIGHT name="CValue">0</WEIGHT>
            <WEIGHT name="CValue1">0</WEIGHT>
            <WEIGHT name="CValuePlus">2</WEIGHT>
            <WEIGHT name="CValuePlus1">3.16992500144231</WEIGHT>
            <WEIGHT name="CValueStar">N/A</WEIGHT>
            <WEIGHT name="CValueStarH">N/A</WEIGHT>
            <WEIGHT name="CValueStarM">0</WEIGHT>
            <WEIGHT name="CValueStarR">N/A</WEIGHT>
            <WEIGHT name="CValueWCard">0</WEIGHT>
            <WEIGHT name="CValueWCardPlus">2</WEIGHT>
            <WEIGHT name="D">1</WEIGHT>
            <WEIGHT name="DDW">0</WEIGHT>
            <WEIGHT name="Freq">1</WEIGHT>
            <WEIGHT name="IM">2</WEIGHT>
            <WEIGHT name="LLR">0.000115129154648748</WEIGHT>
            <WEIGHT name="NormFreq">0.5</WEIGHT>
            <WEIGHT name="iLong">0.5</WEIGHT>
            <WEIGHT name="iTer">0.333333333333333</WEIGHT>
            <WEIGHT name="idf">0:0</WEIGHT>
            <WEIGHT name="ilnc">0</WEIGHT>
            <WEIGHT name="ilncFreq">0</WEIGHT>
            <WEIGHT name="nbdoc4tc">1</WEIGHT>
            <WEIGHT name="tf">0:1</WEIGHT>
            <WEIGHT name="tf-idf">0:0</WEIGHT>
      </TERM_WEIGHTS>
      <LOG_INFORMATION>YaTeA</LOG_INFORMATION>
      <SYNTACTIC_ANALYSIS>
        <HEAD>
        term27
        </HEAD>
        <MODIFIER POSITION="BEFORE">
        term26
        </MODIFIER>
      </SYNTACTIC_ANALYSIS>
    </TERM_CANDIDATE>
    <TERM_CANDIDATE MNP_STATUS="1">
      <ID>term39</ID>
      <FORM>services de l&apos; aviation civile</FORM>
      <LEMMA>service de le aviation civil</LEMMA>
      <MORPHOSYNTACTIC_FEATURES>
	    <SYNTACTIC_CATEGORY>NOM de DET:ART NOM ADJ</SYNTACTIC_CATEGORY>
      </MORPHOSYNTACTIC_FEATURES>
      <HEAD>term40</HEAD>
      <NUMBER_OCCURRENCES>1</NUMBER_OCCURRENCES>
      <LIST_OCCURRENCES>
      <OCCURRENCE>
        <ID>occ12</ID>
        <MNP>1</MNP>
        <DOC>0</DOC>
        <SENTENCE>4</SENTENCE>
        <START_POSITION>64</START_POSITION>
        <END_POSITION>94</END_POSITION>
        </OCCURRENCE>
      </LIST_OCCURRENCES>
      <TERM_CONFIDENCE>0.5</TERM_CONFIDENCE>
      <TERM_WEIGHTS>
            <WEIGHT name="CValue">2.32192809488736</WEIGHT>
            <WEIGHT name="CValue1">2.58496250072116</WEIGHT>
            <WEIGHT name="CValuePlus">2.32192809488736</WEIGHT>
            <WEIGHT name="CValuePlus1">2.58496250072116</WEIGHT>
            <WEIGHT name="CValueStar">N/A</WEIGHT>
            <WEIGHT name="CValueStarH">N/A</WEIGHT>
            <WEIGHT name="CValueStarM">N/A</WEIGHT>
            <WEIGHT name="CValueStarR">0.263034405833794</WEIGHT>
            <WEIGHT name="CValueWCard">0</WEIGHT>
            <WEIGHT name="CValueWCardPlus">0</WEIGHT>
            <WEIGHT name="D">1</WEIGHT>
            <WEIGHT name="DDW">0</WEIGHT>
            <WEIGHT name="Freq">1</WEIGHT>
            <WEIGHT name="IM">2</WEIGHT>
            <WEIGHT name="LLR">0.000115129154648748</WEIGHT>
            <WEIGHT name="NormFreq">0.5</WEIGHT>
            <WEIGHT name="iLong">0.2</WEIGHT>
            <WEIGHT name="iTer">0.166666666666667</WEIGHT>
            <WEIGHT name="idf">0:0</WEIGHT>
            <WEIGHT name="ilnc">0</WEIGHT>
            <WEIGHT name="ilncFreq">0</WEIGHT>
            <WEIGHT name="nbdoc4tc">1</WEIGHT>
            <WEIGHT name="tf">0:1</WEIGHT>
            <WEIGHT name="tf-idf">0:0</WEIGHT>
      </TERM_WEIGHTS>
      <LOG_INFORMATION>YaTeA</LOG_INFORMATION>
      <SYNTACTIC_ANALYSIS>
        <HEAD>
        term40
        </HEAD>
        <MODIFIER POSITION="AFTER">
        term41
        </MODIFIER>
        <PREP>
        de
        </PREP>
        <DETERMINER>
        l'
        </DETERMINER>
      </SYNTACTIC_ANALYSIS>
    </TERM_CANDIDATE>
    <TERM_CANDIDATE MNP_STATUS="0">
      <ID>term16</ID>
      <FORM>300 m</FORM>
      <LEMMA>300 m</LEMMA>
      <MORPHOSYNTACTIC_FEATURES>
	    <SYNTACTIC_CATEGORY>NUM NOM</SYNTACTIC_CATEGORY>
      </MORPHOSYNTACTIC_FEATURES>
      <HEAD>term18</HEAD>
      <NUMBER_OCCURRENCES>1</NUMBER_OCCURRENCES>
      <LIST_OCCURRENCES>
      <OCCURRENCE>
        <ID>occ34</ID>
        <MNP>0</MNP>
        <DOC>0</DOC>
        <SENTENCE>2</SENTENCE>
        <START_POSITION>28</START_POSITION>
        <END_POSITION>33</END_POSITION>
        </OCCURRENCE>
      </LIST_OCCURRENCES>
      <TERM_CONFIDENCE>0.5</TERM_CONFIDENCE>
      <TERM_WEIGHTS>
            <WEIGHT name="CValue">0</WEIGHT>
            <WEIGHT name="CValue1">0</WEIGHT>
            <WEIGHT name="CValuePlus">2</WEIGHT>
            <WEIGHT name="CValuePlus1">3.16992500144231</WEIGHT>
            <WEIGHT name="CValueStar">N/A</WEIGHT>
            <WEIGHT name="CValueStarH">N/A</WEIGHT>
            <WEIGHT name="CValueStarM">0</WEIGHT>
            <WEIGHT name="CValueStarR">N/A</WEIGHT>
            <WEIGHT name="CValueWCard">0</WEIGHT>
            <WEIGHT name="CValueWCardPlus">2</WEIGHT>
            <WEIGHT name="D">1</WEIGHT>
            <WEIGHT name="DDW">0</WEIGHT>
            <WEIGHT name="Freq">1</WEIGHT>
            <WEIGHT name="IM">2</WEIGHT>
            <WEIGHT name="LLR">0.000115129154648748</WEIGHT>
            <WEIGHT name="NormFreq">0.5</WEIGHT>
            <WEIGHT name="iLong">0.5</WEIGHT>
            <WEIGHT name="iTer">0.333333333333333</WEIGHT>
            <WEIGHT name="idf">0:0</WEIGHT>
            <WEIGHT name="ilnc">0</WEIGHT>
            <WEIGHT name="ilncFreq">0</WEIGHT>
            <WEIGHT name="nbdoc4tc">1</WEIGHT>
            <WEIGHT name="tf">0:1</WEIGHT>
            <WEIGHT name="tf-idf">0:0</WEIGHT>
      </TERM_WEIGHTS>
      <LOG_INFORMATION>YaTeA</LOG_INFORMATION>
      <SYNTACTIC_ANALYSIS>
        <HEAD>
        term18
        </HEAD>
        <MODIFIER POSITION="BEFORE">
        term17
        </MODIFIER>
      </SYNTACTIC_ANALYSIS>
    </TERM_CANDIDATE>
  </LIST_TERM_CANDIDATES>
</TERM_EXTRACTION_RESULTS>
